Workbook
Name product_category: products!$A$1:$B$13
Name countries: countries!$A$2:$E$250

Sheet dashboard

Sheet countries
A1: alpha-3 | B1: name | C1: alpha-2 | D1: region | E1: sub-region
A2: AFG | B2: Afghanistan | C2: AF | D2: Asia | E2: Southern Asia
A3: ALA | B3: Åland Islands | C3: AX | D3: Europe | E3: Northern Europe
A4: ALB | B4: Albania | C4: AL | D4: Europe | E4: Southern Europe
A5: DZA | B5: Algeria | C5: DZ | D5: Africa | E5: Northern Africa
A6: ASM | B6: American Samoa | C6: AS | D6: Oceania | E6: Polynesia
A7: AND | B7: Andorra | C7: AD | D7: Europe | E7: Southern Europe
A8: AGO | B8: Angola | C8: AO | D8: Africa | E8: Sub-Saharan Africa
A9: AIA | B9: Anguilla | C9: AI | D9: Americas | E9: Latin America and the Caribbean
A10: ATA | B10: Antarctica | C10: AQ | D10: Antarctica | E10: Antarctica
A11: ATG | B11: Antigua and Barbuda | C11: AG | D11: Americas | E11: Latin America and the Caribbean
A12: ARG | B12: Argentina | C12: AR | D12: Americas | E12: Latin America and the Caribbean
... A250: ZWE | B250: Zimbabwe | C250: ZW | D250: Africa | E250: Sub-Saharan Africa

Sheet events
A1: Product ID | B1: product category | C1: Order ID | D1: Order Date | E1: month number | F1: month of order | G1: day of order | H1: year of order | I1: Ship Date | J1: time of shipment | K1: Order Priority | L1: Country Code | M1: country | N1: region | O1: subregion | P1: Sales Channel | Q1: Units Sold | R1: Unit Price | S1: Unit Cost | T1: total revenue | U1: total cost | V1: total profit | W1: share of units sold | X1: cumulative share of units sold | Y1: share of revenue | Z1: cumulative share of revenue | AA1: share of total profit | AB1: cumulative share of total profit
A2: 2103 | B2: =VLOOKUP($A2,product_category,2, False) -> Cereal | C2: 100640618 | D2: 41920 | E2: =month(D2) -> 10 | F2: =text(D2,"MMM") -> Oct | G2: =Day(D2) -> 8 | H2: =year(D2) -> 2014 | I2: 41930 | J2: =DATEDIF(D2,I2,"D") -> 10 | K2: M | L2: NOR | M2: =VLOOKUP(L2,countries, 2,false) -> Norway | N2: =VLOOKUP(L2,countries, 4,false) -> Europe | O2: =VLOOKUP(L2,countries, 5,false) -> Northern Europe | P2: Online | Q2: 650 | R2: 205.7 | S2: 117.11 | T2: =MULTIPLY(Q2,R2) -> 133705 | U2: =MULTIPLY(Q3,S3) -> 233400.23 | V2: =MINUS(T2,U2) -> -99695.23 | W2: =Q2/totals!B$2 -> 9.8836407e-05 | X2: =W2 -> 9.8836407e-05 | Y2: =T2/totals!B$5 -> 7.8551607e-05 | Z2: =Y2 -> 7.8551607e-05 | AA2: =V2/totals!B$4 -> -0.00019878988 | AB2: =AA2 -> -0.00019878988
A3: 2103 | B3: =VLOOKUP($A3,product_category,2, False) -> Cereal | C3: 100983083 | D3: 42593 | E3: =month(D3) -> 8 | F3: =text(D3,"MMM") -> Aug | G3: =Day(D3) -> 11 | H3: =year(D3) -> 2016 | I3: 42593 | J3: =DATEDIF(D3,I3,"D") -> 0 | K3: C | L3: SRB | M3: =VLOOKUP(L3,countries, 2,false) -> Serbia | N3: =VLOOKUP(L3,countries, 4,false) -> Europe | O3: =VLOOKUP(L3,countries, 5,false) -> Southern Europe | P3: Offline | Q3: 1993 | R3: 205.7 | S3: 117.11 | T3: =MULTIPLY(Q3,R3) -> 409960.1 | U3: =MULTIPLY(Q4,S4) -> 2358420.2 | V3: =MINUS(T3,U3) -> -1948460.1 | W3: =Q3/totals!B$2 -> 0.00030304763 | X3: =W3+X2 -> 0.00040188403 | Y3: =T3/totals!B$5 -> 0.00024085131 | Z3: =Z2+Y3 -> 0.00031940292 | AA3: =V3/totals!B$4 -> -0.0038851825 | AB3: =AB2+AA3 -> -0.0040839724
A4: 7940 | B4: =VLOOKUP($A4,product_category,2, False) -> Household | C4: 101025998 | D4: 41838 | E4: =month(D4) -> 7 | F4: =text(D4,"MMM") -> Jul | G4: =Day(D4) -> 18 | H4: =year(D4) -> 2014 | I4: 41862 | J4: =DATEDIF(D4,I4,"D") -> 24 | K4: M | L4: #N/A | P4: Online | Q4: 4693 | R4: 668.27 | S4: 502.54 | T4: =MULTIPLY(Q4,R4) -> 3136191.1 | U4: =MULTIPLY(Q5,S5) -> 41968.64 | V4: =MINUS(T4,U4) -> 3094222.5 | W4: =Q4/totals!B$2 -> 0.00071359886 | X4: =W4+X3 -> 0.0011154829 | Y4: =T4/totals!B$5 -> 0.0018425104 | Z4: =Z3+Y4 -> 0.0021619133 | AA4: =V4/totals!B$4 -> 0.006169805 | AB4: =AB3+AA4 -> 0.0020858326
A5: 2455 | B5: =VLOOKUP($A5,product_category,2, False) -> Clothes | C5: 102230632 | D5: 42868 | E5: =month(D5) -> 5 | F5: =text(D5,"MMM") -> May | G5: =Day(D5) -> 13 | H5: =year(D5) -> 2017 | I5: 42899 | J5: =DATEDIF(D5,I5,"D") -> 31 | K5: L | L5: MNE | M5: =VLOOKUP(L5,countries, 2,false) -> Montenegro | N5: =VLOOKUP(L5,countries, 4,false) -> Europe | O5: =VLOOKUP(L5,countries, 5,false) -> Southern Europe | P5: Online | Q5: 1171 | R5: 109.28 | S5: 35.84 | T5: =MULTIPLY(Q5,R5) -> 127966.88 | U5: =MULTIPLY(Q6,S6) -> 243129.92 | V5: =MINUS(T5,U5) -> -115163.04 | W5: =Q5/totals!B$2 -> 0.00017805759 | X5: =W5+X4 -> 0.0012935405 | Y5: =T5/totals!B$5 -> 7.5180465e-05 | Z5: =Z4+Y5 -> 0.0022370938 | AA5: =V5/totals!B$4 -> -0.00022963232 | AB5: =AB4+AA5 -> 0.0018562003
A6: 1270 | B6: =VLOOKUP($A6,product_category,2, False) -> Beverages | C6: 103435266 | D6: 41132 | E6: =month(D6) -> 8 | F6: =text(D6,"MMM") -> Aug | G6: =Day(D6) -> 11 | H6: =year(D6) -> 2012 | I6: 41170 | J6: =DATEDIF(D6,I6,"D") -> 38 | K6: H | L6: SRB | M6: =VLOOKUP(L6,countries, 2,false) -> Serbia | N6: =VLOOKUP(L6,countries, 4,false) -> Europe | O6: =VLOOKUP(L6,countries, 5,false) -> Southern Europe | P6: Offline | Q6: 7648 | R6: 47.45 | S6: 31.79 | T6: =MULTIPLY(Q6,R6) -> 362897.6 | U6: =MULTIPLY(Q7,S7) -> 1165411.2 | V6: =MINUS(T6,U6) -> -802513.6 | W6: =Q6/totals!B$2 -> 0.0011629244 | X6: =W6+X5 -> 0.0024564648 | Y6: =T6/totals!B$5 -> 0.00021320212 | Z6: =Z5+Y6 -> 0.0024502959 | AA6: =V6/totals!B$4 -> -0.0016001928 | AB6: =AB5+AA6 -> 0.00025600752
A7: 8681 | B7: =VLOOKUP($A7,product_category,2, False) -> Office Supplies | C7: 103450715 | D7: 42078 | E7: =month(D7) -> 3 | F7: =text(D7,"MMM") -> Mar | G7: =Day(D7) -> 15 | H7: =year(D7) -> 2015 | I7: 42112 | J7: =DATEDIF(D7,I7,"D") -> 34 | K7: H | L7: SVK | M7: =VLOOKUP(L7,countries, 2,false) -> Slovakia | N7: =VLOOKUP(L7,countries, 4,false) -> Europe | O7: =VLOOKUP(L7,countries, 5,false) -> Eastern Europe | P7: Online | Q7: 2220 | R7: 651.21 | S7: 524.96 | T7: =MULTIPLY(Q7,R7) -> 1445686.2 | U7: =MULTIPLY(Q8,S8) -> 46350.16 | V7: =MINUS(T7,U7) -> 1399336 | W7: =Q7/totals!B$2 -> 0.00033756434 | X7: =W7+X6 -> 0.0027940292 | Y7: =T7/totals!B$5 -> 0.00084933977 | Z7: =Z6+Y7 -> 0.0032996357 | AA7: =V7/totals!B$4 -> 0.0027902423 | AB7: =AB6+AA7 -> 0.0030462498
A8: 4594 | B8: =VLOOKUP($A8,product_category,2, False) -> Fruits | C8: 103499639 | D8: 41384 | E8: =month(D8) -> 4 | F8: =text(D8,"MMM") -> Apr | G8: =Day(D8) -> 20 | H8: =year(D8) -> 2013 | I8: 41431 | J8: =DATEDIF(D8,I8,"D") -> 47 | K8: L | L8: FRA | M8: =VLOOKUP(L8,countries, 2,false) -> France | N8: =VLOOKUP(L8,countries, 4,false) -> Europe | O8: =VLOOKUP(L8,countries, 5,false) -> Western Europe | P8: Online | Q8: 6698 | R8: 9.33 | S8: 6.92 | T8: =MULTIPLY(Q8,R8) -> 62492.34 | U8: =MULTIPLY(Q9,S9) -> 401819.67 | V8: =MINUS(T8,U8) -> -339327.33 | W8: =Q8/totals!B$2 -> 0.0010184712 | X8: =W8+X7 -> 0.0038125003 | Y8: =T8/totals!B$5 -> 3.6714212e-05 | Z8: =Z7+Y8 -> 0.0033363499 | AA8: =V8/totals!B$4 -> -0.00067661051 | AB8: =AB7+AA8 -> 0.0023696393
A9: 5988 | B9: =VLOOKUP($A9,product_category,2, False) -> Vegetables | C9: 103762280 | D9: 40859 | E9: =month(D9) -> 11 | F9: =text(D9,"MMM") -> Nov | G9: =Day(D9) -> 12 | H9: =year(D9) -> 2011 | I9: 40891 | J9: =DATEDIF(D9,I9,"D") -> 32 | K9: M | L9: ESP | M9: =VLOOKUP(L9,countries, 2,false) -> Spain | N9: =VLOOKUP(L9,countries, 4,false) -> Europe | O9: =VLOOKUP(L9,countries, 5,false) -> Southern Europe | P9: Online | Q9: 4419 | R9: 154.06 | S9: 90.93 | T9: =MULTIPLY(Q9,R9) -> 680791.14 | U9: =MULTIPLY(Q10,S10) -> 836476.74 | V9: =MINUS(T9,U9) -> -155685.6 | W9: =Q9/totals!B$2 -> 0.00067193551 | X9: =W9+X8 -> 0.0044844359 | Y9: =T9/totals!B$5 -> 0.00039996438 | Z9: =Z8+Y9 -> 0.0037363143 | AA9: =V9/totals!B$4 -> -0.00031043333 | AB9: =AB8+AA9 -> 0.002059206
A10: 7331 | B10: =VLOOKUP($A10,product_category,2, False) -> Baby Food | C10: 103832662 | D10: 41171 | E10: =month(D10) -> 9 | F10: =text(D10,"MMM") -> Sep | G10: =Day(D10) -> 19 | H10: =year(D10) -> 2012 | I10: 41202 | J10: =DATEDIF(D10,I10,"D") -> 31 | K10: H | L10: HRV | M10: =VLOOKUP(L10,countries, 2,false) -> Croatia | N10: =VLOOKUP(L10,countries, 4,false) -> Europe | O10: =VLOOKUP(L10,countries, 5,false) -> Southern Europe | P10: Offline | Q10: 5247 | R10: 255.28 | S10: 159.42 | T10: =MULTIPLY(Q10,R10) -> 1339454.2 | U10: =MULTIPLY(Q11,S11) -> 856659.65 | V10: =MINUS(T10,U10) -> 482794.51 | W10: =Q10/totals!B$2 -> 0.00079783789 | X10: =W10+X9 -> 0.0052822737 | Y10: =T10/totals!B$5 -> 0.00078692851 | Z10: =Z9+Y10 -> 0.0045232428 | AA10: =V10/totals!B$4 -> 0.00096268061 | AB10: =AB9+AA10 -> 0.0030218866
A11: 2103 | B11: =VLOOKUP($A11,product_category,2, False) -> Cereal | C11: 104008615 | D11: 40566 | E11: =month(D11) -> 1 | F11: =text(D11,"MMM") -> Jan | G11: =Day(D11) -> 23 | H11: =year(D11) -> 2011 | I11: 40596 | J11: =DATEDIF(D11,I11,"D") -> 30 | K11: M | L11: DEU | M11: =VLOOKUP(L11,countries, 2,false) -> Germany | N11: =VLOOKUP(L11,countries, 4,false) -> Europe | O11: =VLOOKUP(L11,countries, 5,false) -> Western Europe | P11: Online | Q11: 7315 | R11: 205.7 | S11: 117.11 | T11: =MULTIPLY(Q11,R11) -> 1504695.5 | U11: =MULTIPLY(Q12,S12) -> 1907641.8 | V11: =MINUS(T11,U11) -> -402946.34 | W11: =Q11/totals!B$2 -> 0.0011122897 | X11: =W11+X10 -> 0.0063945634 | Y11: =T11/totals!B$5 -> 0.0008840077 | Z11: =Z10+Y11 -> 0.0054072505 | AA11: =V11/totals!B$4 -> -0.00080346528 | AB11: =AB10+AA11 -> 0.0022184213
A12: 7940 | B12: =VLOOKUP($A12,product_category,2, False) -> Household | C12: 104165685 | D12: 40958 | E12: =month(D12) -> 2 | F12: =text(D12,"MMM") -> Feb | G12: =Day(D12) -> 19 | H12: =year(D12) -> 2012 | I12: 40974 | J12: =DATEDIF(D12,I12,"D") -> 16 | K12: L | L12: ARM | M12: =VLOOKUP(L12,countries, 2,false) -> Armenia | N12: =VLOOKUP(L12,countries, 4,false) -> Asia | O12: =VLOOKUP(L12,countries, 5,false) -> Western Asia | P12: Online | Q12: 3796 | R12: 668.27 | S12: 502.54 | T12: =MULTIPLY(Q12,R12) -> 2536752.9 | U12: =MULTIPLY(Q13,S13) -> 423769.78 | V12: =MINUS(T12,U12) -> 2112983.1 | W12: =Q12/totals!B$2 -> 0.00057720461 | X12: =W12+X11 -> 0.0069717681 | Y12: =T12/totals!B$5 -> 0.0014903408 | Z12: =Z11+Y12 -> 0.0068975913 | AA12: =V12/totals!B$4 -> 0.0042132374 | AB12: =AB11+AA12 -> 0.0064316587
A13: 8875 | B13: =VLOOKUP($A13,product_category,2, False) -> Meat | C13: 104190576 | D13: 42788 | E13: =month(D13) -> 2 | F13: =text(D13,"MMM") -> Feb | G13: =Day(D13) -> 22 | H13: =year(D13) -> 2017 | I13: 42806 | J13: =DATEDIF(D13,I13,"D") -> 18 | K13: C | L13: GEO | M13: =VLOOKUP(L13,countries, 2,false) -> Georgia | N13: =VLOOKUP(L13,countries, 4,false) -> Asia | O13: =VLOOKUP(L13,countries, 5,false) -> Western Asia | P13: Offline | Q13: 1162 | R13: 421.89 | S13: 364.69 | T13: =MULTIPLY(Q13,R13) -> 490236.18 | U13: =MULTIPLY(Q14,S14) -> 50446.8 | V13: =MINUS(T13,U13) -> 439789.38 | W13: =Q13/totals!B$2 -> 0.00017668908 | X13: =W13+X12 -> 0.0071484571 | Y13: =T13/totals!B$5 -> 0.00028801346 | Z13: =Z12+Y13 -> 0.0071856047 | AA13: =V13/totals!B$4 -> 0.00087692942 | AB13: =AB12+AA13 -> 0.0073085881
A14: 4594 | B14: =VLOOKUP($A14,product_category,2, False) -> Fruits | C14: 104245078 | D14: 41360 | E14: =month(D14) -> 3 | F14: =text(D14,"MMM") -> Mar | G14: =Day(D14) -> 27 | H14: =year(D14) -> 2013 | I14: 41385 | J14: =DATEDIF(D14,I14,"D") -> 25 | K14: M | L14: GBR | M14: =VLOOKUP(L14,countries, 2,false) -> United Kingdom | N14: =VLOOKUP(L14,countries, 4,false) -> Europe | O14: =VLOOKUP(L14,countries, 5,false) -> Northern Europe | P14: Offline | Q14: 7290 | R14: 9.33 | S14: 6.92 | T14: =MULTIPLY(Q14,R14) -> 68015.7 | U14: =MULTIPLY(Q15,S15) -> 1128055.9 | V14: =MINUS(T14,U14) -> -1060040.2 | W14: =Q14/totals!B$2 -> 0.0011084883 | X14: =W14+X13 -> 0.0082569455 | Y14: =T14/totals!B$5 -> 3.9959183e-05 | Z14: =Z13+Y14 -> 0.0072255639 | AA14: =V14/totals!B$4 -> -0.0021136946 | AB14: =AB13+AA14 -> 0.0051948935
A15: 7331 | B15: =VLOOKUP($A15,product_category,2, False) -> Baby Food | C15: 104548490 | D15: 41640 | E15: =month(D15) -> 1 | F15: =text(D15,"MMM") -> Jan | G15: =Day(D15) -> 1 | H15: =year(D15) -> 2014 | I15: 41644 | J15: =DATEDIF(D15,I15,"D") -> 4 | K15: M | L15: #N/A | P15: Online | Q15: 7076 | R15: 255.28 | S15: 159.42 | T15: =MULTIPLY(Q15,R15) -> 1806361.3 | U15: =MULTIPLY(Q16,S16) -> 342845.44 | V15: =MINUS(T15,U15) -> 1463515.8 | W15: =Q15/totals!B$2 -> 0.0010759483 | X15: =W15+X14 -> 0.0093328938 | Y15: =T15/totals!B$5 -> 0.0010612362 | Z15: =Z14+Y15 -> 0.0082868001 | AA15: =V15/totals!B$4 -> 0.0029182153 | AB15: =AB14+AA15 -> 0.0081131088
A16: 2455 | B16: =VLOOKUP($A16,product_category,2, False) -> Clothes | C16: 105030000 | D16: 42523 | E16: =month(D16) -> 6 | F16: =text(D16,"MMM") -> Jun | G16: =Day(D16) -> 2 | H16: =year(D16) -> 2016 | I16: 42534 | J16: =DATEDIF(D16,I16,"D") -> 11 | K16: C | L16: SVN | M16: =VLOOKUP(L16,countries, 2,false) -> Slovenia | N16: =VLOOKUP(L16,countries, 4,false) -> Europe | O16: =VLOOKUP(L16,countries, 5,false) -> Southern Europe | P16: Offline | Q16: 9566 | R16: 109.28 | S16: 35.84 | T16: =MULTIPLY(Q16,R16) -> 1045372.5 | U16: =MULTIPLY(Q17,S17) -> 2642355.3 | V16: =MINUS(T16,U16) -> -1596982.8 | W16: =Q16/totals!B$2 -> 0.0014545678 | X16: =W16+X15 -> 0.010787462 | Y16: =T16/totals!B$5 -> 0.0006141557 | Z16: =Z15+Y16 -> 0.0089009558 | AA16: =V16/totals!B$4 -> -0.0031843453 | AB16: =AB15+AA16 -> 0.0049287635
A17: 7940 | B17: =VLOOKUP($A17,product_category,2, False) -> Household | C17: 107651269 | D17: 41575 | E17: =month(D17) -> 10 | F17: =text(D17,"MMM") -> Oct | G17: =Day(D17) -> 28 | H17: =year(D17) -> 2013 | I17: 41589 | J17: =DATEDIF(D17,I17,"D") -> 14 | K17: M | L17: HRV | M17: =VLOOKUP(L17,countries, 2,false) -> Croatia | N17: =VLOOKUP(L17,countries, 4,false) -> Europe | O17: =VLOOKUP(L17,countries, 5,false) -> Southern Europe | P17: Online | Q17: 5258 | R17: 668.27 | S17: 502.54 | T17: =MULTIPLY(Q17,R17) -> 3513763.7 | U17: =MULTIPLY(Q18,S18) -> 1438765.5 | V17: =MINUS(T17,U17) -> 2074998.2 | W17: =Q17/totals!B$2 -> 0.0007995105 | X17: =W17+X16 -> 0.011586972 | Y17: =T17/totals!B$5 -> 0.002064334 | Z17: =Z16+Y17 -> 0.01096529 | AA17: =V17/totals!B$4 -> 0.0041374963 | AB17: =AB16+AA17 -> 0.0090662598
A18: 7331 | B18: =VLOOKUP($A18,product_category,2, False) -> Baby Food | C18: 108407437 | D18: 42054 | E18: =month(D18) -> 2 | F18: =text(D18,"MMM") -> Feb | G18: =Day(D18) -> 19 | H18: =year(D18) -> 2015 | I18: 42090 | J18: =DATEDIF(D18,I18,"D") -> 36 | K18: C | L18: ROU | M18: =VLOOKUP(L18,countries, 2,false) -> Romania | N18: =VLOOKUP(L18,countries, 4,false) -> Europe | O18: =VLOOKUP(L18,countries, 5,false) -> Eastern Europe | P18: Offline | Q18: 9025 | R18: 255.28 | S18: 159.42 | T18: =MULTIPLY(Q18,R18) -> 2303902 | U18: =MULTIPLY(Q19,S19) -> 175902.72 | V18: =MINUS(T18,U18) -> 2127999.3 | W18: =Q18/totals!B$2 -> 0.0013723055 | X18: =W18+X17 -> 0.012959278 | Y18: =T18/totals!B$5 -> 0.001353541 | Z18: =Z17+Y18 -> 0.012318831 | AA18: =V18/totals!B$4 -> 0.0042431792 | AB18: =AB17+AA18 -> 0.013309439
A19: 2455 | B19: =VLOOKUP($A19,product_category,2, False) -> Clothes | C19: 109914195 | D19: 40980 | E19: =month(D19) -> 3 | F19: =text(D19,"MMM") -> Mar | G19: =Day(D19) -> 12 | H19: =year(D19) -> 2012 | I19: 41015 | J19: =DATEDIF(D19,I19,"D") -> 35 | K19: M | L19: POL | M19: =VLOOKUP(L19,countries, 2,false) -> Poland | N19: =VLOOKUP(L19,countries, 4,false) -> Europe | O19: =VLOOKUP(L19,countries, 5,false) -> Eastern Europe | P19: Offline | Q19: 4908 | R19: 109.28 | S19: 35.84 | T19: =MULTIPLY(Q19,R19) -> 536346.24 | U19: =MULTIPLY(Q20,S20) -> 777331.92 | V19: =MINUS(T19,U19) -> -240985.68 | W19: =Q19/totals!B$2 -> 0.0007462909 | X19: =W19+X18 -> 0.013705568 | Y19: =T19/totals!B$5 -> 0.00031510309 | Z19: =Z18+Y19 -> 0.012633934 | AA19: =V19/totals!B$4 -> -0.00048051963 | AB19: =AB18+AA19 -> 0.012828919
A20: 7331 | B20: =VLOOKUP($A20,product_category,2, False) -> Baby Food | C20: 111063039 | D20: 41055 | E20: =month(D20) -> 5 | F20: =text(D20,"MMM") -> May | G20: =Day(D20) -> 26 | H20: =year(D20) -> 2012 | I20: 41103 | J20: =DATEDIF(D20,I20,"D") -> 48 | K20: L | L20: LUX | M20: =VLOOKUP(L20,countries, 2,false) -> Luxembourg | N20: =VLOOKUP(L20,countries, 4,false) -> Europe | O20: =VLOOKUP(L20,countries, 5,false) -> Western Europe | P20: Online | Q20: 4876 | R20: 255.28 | S20: 159.42 | T20: =MULTIPLY(Q20,R20) -> 1244745.3 | U20: =MULTIPLY(Q21,S21) -> 3319773.1 | V20: =MINUS(T20,U20) -> -2075027.8 | W20: =Q20/totals!B$2 -> 0.00074142511 | X20: =W20+X19 -> 0.014446994 | Y20: =T20/totals!B$5 -> 0.0007312871 | Z20: =Z19+Y20 -> 0.013365221 | AA20: =V20/totals!B$4 -> -0.0041375554 | AB20: =AB19+AA20 -> 0.0086913641
A21: 8875 | B21: =VLOOKUP($A21,product_category,2, False) -> Meat | C21: 111246287 | D21: 42895 | E21: =month(D21) -> 6 | F21: =text(D21,"MMM") -> Jun | G21: =Day(D21) -> 9 | H21: =year(D21) -> 2017 | I21: 42918 | J21: =DATEDIF(D21,I21,"D") -> 23 | K21: M | L21: CYP | M21: =VLOOKUP(L21,countries, 2,false) -> Cyprus | N21: =VLOOKUP(L21,countries, 4,false) -> Asia | O21: =VLOOKUP(L21,countries, 5,false) -> Western Asia | P21: Offline | Q21: 9103 | R21: 421.89 | S21: 364.69 | T21: =MULTIPLY(Q21,R21) -> 3840464.7 | U21: =MULTIPLY(Q22,S22) -> 20863.8 | V21: =MINUS(T21,U21) -> 3819600.9 | W21: =Q21/totals!B$2 -> 0.0013841659 | X21: =W21+X20 -> 0.015831159 | Y21: =T21/totals!B$5 -> 0.0022562707 | Z21: =Z20+Y21 -> 0.015621492 | AA21: =V21/totals!B$4 -> 0.007616192 | AB21: =AB20+AA21 -> 0.016307556
A22: 4594 | B22: =VLOOKUP($A22,product_category,2, False) -> Fruits | C22: 111496055 | D22: 40661 | E22: =month(D22) -> 4 | F22: =text(D22,"MMM") -> Apr | G22: =Day(D22) -> 28 | H22: =year(D22) -> 2011 | I22: 40698 | J22: =DATEDIF(D22,I22,"D") -> 37 | K22: M | L22: BEL | M22: =VLOOKUP(L22,countries, 2,false) -> Belgium | N22: =VLOOKUP(L22,countries, 4,false) -> Europe | O22: =VLOOKUP(L22,countries, 5,false) -> Western Europe | P22: Online | Q22: 3015 | R22: 9.33 | S22: 6.92 | T22: =MULTIPLY(Q22,R22) -> 28129.95 | U22: =MULTIPLY(Q23,S23) -> 77478.12 | V22: =MINUS(T22,U22) -> -49348.17 | W22: =Q22/totals!B$2 -> 0.00045844887 | X22: =W22+X21 -> 0.016289608 | Y22: =T22/totals!B$5 -> 1.6526329e-05 | Z22: =Z21+Y22 -> 0.015638018 | AA22: =V22/totals!B$4 -> -9.8399061e-05 | AB22: =AB21+AA22 -> 0.016209157
A23: 7331 | B23: =VLOOKUP($A23,product_category,2, False) -> Baby Food | C23: 111893022 | D23: 42671 | E23: =month(D23) -> 10 | F23: =text(D23,"MMM") -> Oct | G23: =Day(D23) -> 28 | H23: =year(D23) -> 2016 | I23: 42706 | J23: =DATEDIF(D23,I23,"D") -> 35 | K23: L | L23: SVN | M23: =VLOOKUP(L23,countries, 2,false) -> Slovenia | N23: =VLOOKUP(L23,countries, 4,false) -> Europe | O23: =VLOOKUP(L23,countries, 5,false) -> Southern Europe | P23: Online | Q23: 486 | R23: 255.28 | S23: 159.42 | T23: =MULTIPLY(Q23,R23) -> 124066.08 | U23: =MULTIPLY(Q24,S24) -> 11549.12 | V23: =MINUS(T23,U23) -> 112516.96 | W23: =Q23/totals!B$2 -> 7.3899221e-05 | X23: =W23+X22 -> 0.016363508 | Y23: =T23/totals!B$5 -> 7.2888747e-05 | Z23: =Z22+Y23 -> 0.015710907 | AA23: =V23/totals!B$4 -> 0.0002243561 | AB23: =AB22+AA23 -> 0.016433513
A24: 8681 | B24: =VLOOKUP($A24,product_category,2, False) -> Office Supplies | C24: 112330758 | D24: 42719 | E24: =month(D24) -> 12 | F24: =text(D24,"MMM") -> Dec | G24: =Day(D24) -> 15 | H24: =year(D24) -> 2016 | I24: 42746 | J24: =DATEDIF(D24,I24,"D") -> 27 | K24: C | L24: LTU | M24: =VLOOKUP(L24,countries, 2,false) -> Lithuania | N24: =VLOOKUP(L24,countries, 4,false) -> Europe | O24: =VLOOKUP(L24,countries, 5,false) -> Northern Europe | P24: Offline | Q24: 22 | R24: 651.21 | S24: 524.96 | T24: =MULTIPLY(Q24,R24) -> 14326.62 | U24: =MULTIPLY(Q25,S25) -> 875572.25 | V24: =MINUS(T24,U24) -> -861245.63 | W24: =Q24/totals!B$2 -> 3.3452322e-06 | X24: =W24+X23 -> 0.016366853 | Y24: =T24/totals!B$5 -> 8.4168806e-06 | Z24: =Z23+Y24 -> 0.015719324 | AA24: =V24/totals!B$4 -> -0.001717303 | AB24: =AB23+AA24 -> 0.01471621
A25: 8293 | B25: =VLOOKUP($A25,product_category,2, False) -> Cosmetics | C25: 113524663 | D25: 40480 | E25: =month(D25) -> 10 | F25: =text(D25,"MMM") -> Oct | G25: =Day(D25) -> 29 | H25: =year(D25) -> 2010 | I25: 40521 | J25: =DATEDIF(D25,I25,"D") -> 41 | K25: L | L25: RUS | M25: =VLOOKUP(L25,countries, 2,false) -> Russia | N25: =VLOOKUP(L25,countries, 4,false) -> Europe | O25: =VLOOKUP(L25,countries, 5,false) -> Eastern Europe | P25: Online | Q25: 3325 | R25: 437.2 | S25: 263.33 | T25: =MULTIPLY(Q25,R25) -> 1453690 | U25: =MULTIPLY(Q26,S26) -> 43935.08 | V25: =MINUS(T25,U25) -> 1409754.9 | W25: =Q25/totals!B$2 -> 0.00050558623 | X25: =W25+X24 -> 0.016872439 | Y25: =T25/totals!B$5 -> 0.000854042 | Z25: =Z24+Y25 -> 0.016573366 | AA25: =V25/totals!B$4 -> 0.0028110173 | AB25: =AB24+AA25 -> 0.017527227
A26: 4594 | B26: =VLOOKUP($A26,product_category,2, False) -> Fruits | C26: 114954173 | D26: 40212 | E26: =month(D26) -> 2 | F26: =text(D26,"MMM") -> Feb | G26: =Day(D26) -> 3 | H26: =year(D26) -> 2010 | I26: 40220 | J26: =DATEDIF(D26,I26,"D") -> 8 | K26: C | L26: MLT | M26: =VLOOKUP(L26,countries, 2,false) -> Malta | N26: =VLOOKUP(L26,countries, 4,false) -> Europe | O26: =VLOOKUP(L26,countries, 5,false) -> Southern Europe | P26: Offline | Q26: 6349 | R26: 9.33 | S26: 6.92 | T26: =MULTIPLY(Q26,R26) -> 59236.17 | U26: =MULTIPLY(Q27,S27) -> 3872105 | V26: =MINUS(T26,U26) -> -3812868.8 | W26: =Q26/totals!B$2 -> 0.00096540361 | X26: =W26+X25 -> 0.017837843 | Y26: =T26/totals!B$5 -> 3.4801214e-05 | Z26: =Z25+Y26 -> 0.016608167 | AA26: =V26/totals!B$4 -> -0.0076027684 | AB26: =AB25+AA26 -> 0.009924459
A27: 8681 | B27: =VLOOKUP($A27,product_category,2, False) -> Office Supplies | C27: 115363156 | D27: 42342 | E27: =month(D27) -> 12 | F27: =text(D27,"MMM") -> Dec | G27: =Day(D27) -> 4 | H27: =year(D27) -> 2015 | I27: 42379 | J27: =DATEDIF(D27,I27,"D") -> 37 | K27: H | L27: UKR | M27: =VLOOKUP(L27,countries, 2,false) -> Ukraine | N27: =VLOOKUP(L27,countries, 4,false) -> Europe | O27: =VLOOKUP(L27,countries, 5,false) -> Eastern Europe | P27: Offline | Q27: 7376 | R27: 651.21 | S27: 524.96 | T27: =MULTIPLY(Q27,R27) -> 4803325 | U27: =MULTIPLY(Q28,S28) -> 47145.96 | V27: =MINUS(T27,U27) -> 4756179 | W27: =Q27/totals!B$2 -> 0.0011215651 | X27: =W27+X26 -> 0.018959408 | Y27: =T27/totals!B$5 -> 0.0028219505 | Z27: =Z26+Y27 -> 0.019430117 | AA27: =V27/totals!B$4 -> 0.0094837062 | AB27: =AB26+AA27 -> 0.019408165
A28: 4594 | B28: =VLOOKUP($A28,product_category,2, False) -> Fruits | C28: 117929494 | D28: 42028 | E28: =month(D28) -> 1 | F28: =text(D28,"MMM") -> Jan | G28: =Day(D28) -> 24 | H28: =year(D28) -> 2015 | I28: 42065 | J28: =DATEDIF(D28,I28,"D") -> 37 | K28: H | L28: #N/A | P28: Offline | Q28: 6813 | R28: 9.33 | S28: 6.92 | T28: =MULTIPLY(Q28,R28) -> 63565.29 | U28: =MULTIPLY(Q29,S29) -> 320869.92 | V28: =MINUS(T28,U28) -> -257304.63 | W28: =Q28/totals!B$2 -> 0.0010359576 | X28: =W28+X27 -> 0.019995365 | Y28: =T28/totals!B$5 -> 3.734457e-05 | Z28: =Z27+Y28 -> 0.019467462 | AA28: =V28/totals!B$4 -> -0.00051305923 | AB28: =AB27+AA28 -> 0.018895106
A29: 8969 | B29: =VLOOKUP($A29,product_category,2, False) -> Snacks | C29: 118086564 | D29: 42419 | E29: =month(D29) -> 2 | F29: =text(D29,"MMM") -> Feb | G29: =Day(D29) -> 19 | H29: =year(D29) -> 2016 | I29: 42442 | J29: =DATEDIF(D29,I29,"D") -> 23 | K29: M | L29: NOR | M29: =VLOOKUP(L29,countries, 2,false) -> Norway | N29: =VLOOKUP(L29,countries, 4,false) -> Europe | O29: =VLOOKUP(L29,countries, 5,false) -> Northern Europe | P29: Online | Q29: 3293 | R29: 152.58 | S29: 97.44 | T29: =MULTIPLY(Q29,R29) -> 502445.94 | U29: =MULTIPLY(Q30,S30) -> 346645.6 | V29: =MINUS(T29,U29) -> 155800.34 | W29: =Q29/totals!B$2 -> 0.00050072044 | X29: =W29+X28 -> 0.020496086 | Y29: =T29/totals!B$5 -> 0.00029518669 | Z29: =Z28+Y29 -> 0.019762649 | AA29: =V29/totals!B$4 -> 0.00031066212 | AB29: =AB28+AA29 -> 0.019205768
A30: 2103 | B30: =VLOOKUP($A30,product_category,2, False) -> Cereal | C30: 118659913 | D30: 41853 | E30: =month(D30) -> 8 | F30: =text(D30,"MMM") -> Aug | G30: =Day(D30) -> 2 | H30: =year(D30) -> 2014 | I30: 41868 | J30: =DATEDIF(D30,I30,"D") -> 15 | K30: C | L30: CZE | M30: =VLOOKUP(L30,countries, 2,false) -> Czech Republic | N30: =VLOOKUP(L30,countries, 4,false) -> Europe | O30: =VLOOKUP(L30,countries, 5,false) -> Eastern Europe | P30: Online | Q30: 2960 | R30: 205.7 | S30: 117.11 | T30: =MULTIPLY(Q30,R30) -> 608872 | U30: =MULTIPLY(Q31,S31) -> 196146.72 | V30: =MINUS(T30,U30) -> 412725.28 | W30: =Q30/totals!B$2 -> 0.00045008579 | X30: =W30+X29 -> 0.020946172 | Y30: =T30/totals!B$5 -> 0.00035771193 | Z30: =Z29+Y30 -> 0.020120361 | AA30: =V30/totals!B$4 -> 0.00082296425 | AB30: =AB29+AA30 -> 0.020028732
A31: 8969 | B31: =VLOOKUP($A31,product_category,2, False) -> Snacks | C31: 118859469 | D31: 40696 | E31: =month(D31) -> 6 | F31: =text(D31,"MMM") -> Jun | G31: =Day(D31) -> 2 | H31: =year(D31) -> 2011 | I31: 40725 | J31: =DATEDIF(D31,I31,"D") -> 29 | K31: L | L31: #N/A | P31: Offline | Q31: 2013 | R31: 152.58 | S31: 97.44 | T31: =MULTIPLY(Q31,R31) -> 307143.54 | U31: =MULTIPLY(Q32,S32) -> 29411.73 | V31: =MINUS(T31,U31) -> 277731.81 | W31: =Q31/totals!B$2 -> 0.00030608875 | X31: =W31+X30 -> 0.02125226 | Y31: =T31/totals!B$5 -> 0.00018044664 | Z31: =Z30+Y31 -> 0.020300807 | AA31: =V31/totals!B$4 -> 0.00055379053 | AB31: =AB30+AA31 -> 0.020582523
A32: 3127 | B32: =VLOOKUP($A32,product_category,2, False) -> Personal Care | C32: 119935786 | D32: 42018 | E32: =month(D32) -> 1 | F32: =text(D32,"MMM") -> Jan | G32: =Day(D32) -> 14 | H32: =year(D32) -> 2015 | I32: 42031 | J32: =DATEDIF(D32,I32,"D") -> 13 | K32: L | L32: ROU | M32: =VLOOKUP(L32,countries, 2,false) -> Romania | N32: =VLOOKUP(L32,countries, 4,false) -> Europe | O32: =VLOOKUP(L32,countries, 5,false) -> Eastern Europe | P32: Offline | Q32: 519 | R32: 81.73 | S32: 56.67 | T32: =MULTIPLY(Q32,R32) -> 42417.87 | U32: =MULTIPLY(Q33,S33) -> 213702.57 | V32: =MINUS(T32,U32) -> -171284.7 | W32: =Q32/totals!B$2 -> 7.8917069e-05 | X32: =W32+X31 -> 0.021331177 | Y32: =T32/totals!B$5 -> 2.4920473e-05 | Z32: =Z31+Y32 -> 0.020325728 | AA32: =V32/totals!B$4 -> -0.00034153756 | AB32: =AB31+AA32 -> 0.020240985
A33: 3127 | B33: =VLOOKUP($A33,product_category,2, False) -> Personal Care | C33: 120419871 | D33: 42137 | E33: =month(D33) -> 5 | F33: =text(D33,"MMM") -> May | G33: =Day(D33) -> 13 | H33: =year(D33) -> 2015 | I33: 42181 | J33: =DATEDIF(D33,I33,"D") -> 44 | K33: H | L33: LTU | M33: =VLOOKUP(L33,countries, 2,false) -> Lithuania | N33: =VLOOKUP(L33,countries, 4,false) -> Europe | O33: =VLOOKUP(L33,countries, 5,false) -> Northern Europe | P33: Online | Q33: 3771 | R33: 81.73 | S33: 56.67 | T33: =MULTIPLY(Q33,R33) -> 308203.83 | U33: =MULTIPLY(Q34,S34) -> 61352.72 | V33: =MINUS(T33,U33) -> 246851.11 | W33: =Q33/totals!B$2 -> 0.00057340321 | X33: =W33+X32 -> 0.021904581 | Y33: =T33/totals!B$5 -> 0.00018106956 | Z33: =Z32+Y33 -> 0.020506797 | AA33: =V33/totals!B$4 -> 0.00049221516 | AB33: =AB32+AA33 -> 0.0207332
A34: 4594 | B34: =VLOOKUP($A34,product_category,2, False) -> Fruits | C34: 120977771 | D34: 40625 | E34: =month(D34) -> 3 | F34: =text(D34,"MMM") -> Mar | G34: =Day(D34) -> 23 | H34: =year(D34) -> 2011 | I34: 40665 | J34: =DATEDIF(D34,I34,"D") -> 40 | K34: M | L34: ARM | M34: =VLOOKUP(L34,countries, 2,false) -> Armenia | N34: =VLOOKUP(L34,countries, 4,false) -> Asia | O34: =VLOOKUP(L34,countries, 5,false) -> Western Asia | P34: Online | Q34: 8866 | R34: 9.33 | S34: 6.92 | T34: =MULTIPLY(Q34,R34) -> 82719.78 | U34: =MULTIPLY(Q35,S35) -> 56155.8 | V34: =MINUS(T34,U34) -> 26563.98 | W34: =Q34/totals!B$2 -> 0.0013481286 | X34: =W34+X33 -> 0.023252709 | Y34: =T34/totals!B$5 -> 4.8597821e-05 | Z34: =Z33+Y34 -> 0.020555395 | AA34: =V34/totals!B$4 -> 5.2967935e-05 | AB34: =AB33+AA34 -> 0.020786168
A35: 4594 | B35: =VLOOKUP($A35,product_category,2, False) -> Fruits | C35: 121380746 | D35: 42695 | E35: =month(D35) -> 11 | F35: =text(D35,"MMM") -> Nov | G35: =Day(D35) -> 21 | H35: =year(D35) -> 2016 | I35: 42722 | J35: =DATEDIF(D35,I35,"D") -> 27 | K35: C | L35: MLT | M35: =VLOOKUP(L35,countries, 2,false) -> Malta | N35: =VLOOKUP(L35,countries, 4,false) -> Europe | O35: =VLOOKUP(L35,countries, 5,false) -> Southern Europe | P35: Online | Q35: 8115 | R35: 9.33 | S35: 6.92 | T35: =MULTIPLY(Q35,R35) -> 75712.95 | U35: =MULTIPLY(Q36,S36) -> 166643.18 | V35: =MINUS(T35,U35) -> -90930.23 | W35: =Q35/totals!B$2 -> 0.0012339345 | X35: =W35+X34 -> 0.024486644 | Y35: =T35/totals!B$5 -> 4.4481312e-05 | Z35: =Z34+Y35 -> 0.020599876 | AA35: =V35/totals!B$4 -> -0.00018131269 | AB35: =AB34+AA35 -> 0.020604856
A36: 1270 | B36: =VLOOKUP($A36,product_category,2, False) -> Beverages | C36: 121945512 | D36: 42833 | E36: =month(D36) -> 4 | F36: =text(D36,"MMM") -> Apr | G36: =Day(D36) -> 8 | H36: =year(D36) -> 2017 | I36: 42837 | J36: =DATEDIF(D36,I36,"D") -> 4 | K36: C | L36: GBR | M36: =VLOOKUP(L36,countries, 2,false) -> United Kingdom | N36: =VLOOKUP(L36,countries, 4,false) -> Europe | O36: =VLOOKUP(L36,countries, 5,false) -> Northern Europe | P36: Online | Q36: 5242 | R36: 47.45 | S36: 31.79 | T36: =MULTIPLY(Q36,R36) -> 248732.9 | U36: =MULTIPLY(Q37,S37) -> 128463.39 | V36: =MINUS(T36,U36) -> 120269.51 | W36: =Q36/totals!B$2 -> 0.00079707761 | X36: =W36+X35 -> 0.025283721 | Y36: =T36/totals!B$5 -> 0.00014613043 | Z36: =Z35+Y36 -> 0.020746007 | AA36: =V36/totals!B$4 -> 0.0002398145 | AB36: =AB35+AA36 -> 0.02084467
A37: 1270 | B37: =VLOOKUP($A37,product_category,2, False) -> Beverages | C37: 122144210 | D37: 42852 | E37: =month(D37) -> 4 | F37: =text(D37,"MMM") -> Apr | G37: =Day(D37) -> 27 | H37: =year(D37) -> 2017 | I37: 42879 | J37: =DATEDIF(D37,I37,"D") -> 27 | K37: C | L37: MNE | M37: =VLOOKUP(L37,countries, 2,false) -> Montenegro | N37: =VLOOKUP(L37,countries, 4,false) -> Europe | O37: =VLOOKUP(L37,countries, 5,false) -> Southern Europe | P37: Offline | Q37: 4041 | R37: 47.45 | S37: 31.79 | T37: =MULTIPLY(Q37,R37) -> 191745.45 | U37: =MULTIPLY(Q38,S38) -> 50959.37 | V37: =MINUS(T37,U37) -> 140786.08 | W37: =Q37/totals!B$2 -> 0.00061445834 | X37: =W37+X36 -> 0.02589818 | Y37: =T37/totals!B$5 -> 0.00011265034 | Z37: =Z36+Y37 -> 0.020858657 | AA37: =V37/totals!B$4 -> 0.00028072405 | AB37: =AB36+AA37 -> 0.021125394
A38: 1270 | B38: =VLOOKUP($A38,product_category,2, False) -> Beverages | C38: 122372519 | D38: 42379 | E38: =month(D38) -> 1 | F38: =text(D38,"MMM") -> Jan | G38: =Day(D38) -> 10 | H38: =year(D38) -> 2016 | I38: 42382 | J38: =DATEDIF(D38,I38,"D") -> 3 | K38: L | L38: PRT | M38: =VLOOKUP(L38,countries, 2,false) -> Portugal | N38: =VLOOKUP(L38,countries, 4,false) -> Europe | O38: =VLOOKUP(L38,countries, 5,false) -> Southern Europe | P38: Offline | Q38: 1603 | R38: 47.45 | S38: 31.79 | T38: =MULTIPLY(Q38,R38) -> 76062.35 | U38: =MULTIPLY(Q39,S39) -> 242208.01 | V38: =MINUS(T38,U38) -> -166145.66 | W38: =Q38/totals!B$2 -> 0.00024374578 | X38: =W38+X37 -> 0.026141925 | Y38: =T38/totals!B$5 -> 4.4686585e-05 | Z38: =Z37+Y38 -> 0.020903344 | AA38: =V38/totals!B$4 -> -0.00033129044 | AB38: =AB37+AA38 -> 0.020794104
A39: 1270 | B39: =VLOOKUP($A39,product_category,2, False) -> Beverages | C39: 122967326 | D39: 42818 | E39: =month(D39) -> 3 | F39: =text(D39,"MMM") -> Mar | G39: =Day(D39) -> 24 | H39: =year(D39) -> 2017 | I39: 42850 | J39: =DATEDIF(D39,I39,"D") -> 32 | K39: H | L39: BLR | M39: =VLOOKUP(L39,countries, 2,false) -> Belarus | N39: =VLOOKUP(L39,countries, 4,false) -> Europe | O39: =VLOOKUP(L39,countries, 5,false) -> Eastern Europe | P39: Online | Q39: 7619 | R39: 47.45 | S39: 31.79 | T39: =MULTIPLY(Q39,R39) -> 361521.55 | U39: =MULTIPLY(Q40,S40) -> 445897.74 | V39: =MINUS(T39,U39) -> -84376.19 | W39: =Q39/totals!B$2 -> 0.0011585147 | X39: =W39+X38 -> 0.02730044 | Y39: =T39/totals!B$5 -> 0.00021239369 | Z39: =Z38+Y39 -> 0.021115737 | AA39: =V39/totals!B$4 -> -0.00016824409 | AB39: =AB38+AA39 -> 0.02062586
A40: 7331 | B40: =VLOOKUP($A40,product_category,2, False) -> Baby Food | C40: 123086202 | D40: 41641 | E40: =month(D40) -> 1 | F40: =text(D40,"MMM") -> Jan | G40: =Day(D40) -> 2 | H40: =year(D40) -> 2014 | I40: 41690 | J40: =DATEDIF(D40,I40,"D") -> 49 | K40: M | L40: EST | M40: =VLOOKUP(L40,countries, 2,false) -> Estonia | N40: =VLOOKUP(L40,countries, 4,false) -> Europe | O40: =VLOOKUP(L40,countries, 5,false) -> Northern Europe | P40: Offline | Q40: 2797 | R40: 255.28 | S40: 159.42 | T40: =MULTIPLY(Q40,R40) -> 714018.16 | U40: =MULTIPLY(Q41,S41) -> 972247.22 | V40: =MINUS(T40,U40) -> -258229.06 | W40: =Q40/totals!B$2 -> 0.00042530066 | X40: =W40+X39 -> 0.027725741 | Y40: =T40/totals!B$5 -> 0.00041948524 | Z40: =Z39+Y40 -> 0.021535223 | AA40: =V40/totals!B$4 -> -0.00051490252 | AB40: =AB39+AA40 -> 0.020110957
A41: 2103 | B41: =VLOOKUP($A41,product_category,2, False) -> Cereal | C41: 123544108 | D41: 40311 | E41: =month(D41) -> 5 | F41: =text(D41,"MMM") -> May | G41: =Day(D41) -> 13 | H41: =year(D41) -> 2010 | I41: 40351 | J41: =DATEDIF(D41,I41,"D") -> 40 | K41: M | L41: AUT | M41: =VLOOKUP(L41,countries, 2,false) -> Austria | N41: =VLOOKUP(L41,countries, 4,false) -> Europe | O41: =VLOOKUP(L41,countries, 5,false) -> Western Europe | P41: Online | Q41: 8302 | R41: 205.7 | S41: 117.11 | T41: =MULTIPLY(Q41,R41) -> 1707721.4 | U41: =MULTIPLY(Q42,S42) -> 163337.02 | V41: =MINUS(T41,U41) -> 1544384.4 | W41: =Q41/totals!B$2 -> 0.001262369 | X41: =W41+X40 -> 0.02898811 | Y41: =T41/totals!B$5 -> 0.0010032853 | Z41: =Z40+Y41 -> 0.022538508 | AA41: =V41/totals!B$4 -> 0.0030794652 | AB41: =AB40+AA41 -> 0.023190422
A42: 1270 | B42: =VLOOKUP($A42,product_category,2, False) -> Beverages | C42: 123938930 | D42: 41114 | E42: =month(D42) -> 7 | F42: =text(D42,"MMM") -> Jul | G42: =Day(D42) -> 24 | H42: =year(D42) -> 2012 | I42: 41123 | J42: =DATEDIF(D42,I42,"D") -> 9 | K42: M | L42: BLR | M42: =VLOOKUP(L42,countries, 2,false) -> Belarus | N42: =VLOOKUP(L42,countries, 4,false) -> Europe | O42: =VLOOKUP(L42,countries, 5,false) -> Eastern Europe | P42: Online | Q42: 5138 | R42: 47.45 | S42: 31.79 | T42: =MULTIPLY(Q42,R42) -> 243798.1 | U42: =MULTIPLY(Q43,S43) -> 940588.32 | V42: =MINUS(T42,U42) -> -696790.22 | W42: =Q42/totals!B$2 -> 0.00078126378 | X42: =W42+X41 -> 0.029769374 | Y42: =T42/totals!B$5 -> 0.00014323124 | Z42: =Z41+Y42 -> 0.022681739 | AA42: =V42/totals!B$4 -> -0.0013893829 | AB42: =AB41+AA42 -> 0.02180104
A43: 8969 | B43: =VLOOKUP($A43,product_category,2, False) -> Snacks | C43: 125339686 | D43: 42927 | E43: =month(D43) -> 7 | F43: =text(D43,"MMM") -> Jul | G43: =Day(D43) -> 11 | H43: =year(D43) -> 2017 | I43: 42940 | J43: =DATEDIF(D43,I43,"D") -> 13 | K43: L | L43: MKD | M43: =VLOOKUP(L43,countries, 2,false) -> Macedonia | N43: =VLOOKUP(L43,countries, 4,false) -> Europe | O43: =VLOOKUP(L43,countries, 5,false) -> Southern Europe | P43: Online | Q43: 9653 | R43: 152.58 | S43: 97.44 | T43: =MULTIPLY(Q43,R43) -> 1472854.7 | U43: =MULTIPLY(Q44,S44) -> 286568.17 | V43: =MINUS(T43,U43) -> 1186286.6 | W43: =Q43/totals!B$2 -> 0.0014677967 | X43: =W43+X42 -> 0.03123717 | Y43: =T43/totals!B$5 -> 0.00086530127 | Z43: =Z42+Y43 -> 0.02354704 | AA43: =V43/totals!B$4 -> 0.0023654268 | AB43: =AB42+AA43 -> 0.024166466
A44: 2103 | B44: =VLOOKUP($A44,product_category,2, False) -> Cereal | C44: 125349128 | D44: 41047 | E44: =month(D44) -> 5 | F44: =text(D44,"MMM") -> May | G44: =Day(D44) -> 18 | H44: =year(D44) -> 2012 | I44: 41066 | J44: =DATEDIF(D44,I44,"D") -> 19 | K44: L | L44: SMR | M44: =VLOOKUP(L44,countries, 2,false) -> San Marino | N44: =VLOOKUP(L44,countries, 4,false) -> Europe | O44: =VLOOKUP(L44,countries, 5,false) -> Southern Europe | P44: Offline | Q44: 2447 | R44: 205.7 | S44: 117.11 | T44: =MULTIPLY(Q44,R44) -> 503347.9 | U44: =MULTIPLY(Q45,S45) -> 918578.04 | V44: =MINUS(T44,U44) -> -415230.14 | W44: =Q44/totals!B$2 -> 0.00037208106 | X44: =W44+X43 -> 0.031609251 | Y44: =T44/totals!B$5 -> 0.00029571659 | Z44: =Z43+Y44 -> 0.023842757 | AA44: =V44/totals!B$4 -> -0.00082795888 | AB44: =AB43+AA44 -> 0.023338507
A45: 7331 | B45: =VLOOKUP($A45,product_category,2, False) -> Baby Food | C45: 126948583 | D45: 42879 | E45: =month(D45) -> 5 | F45: =text(D45,"MMM") -> May | G45: =Day(D45) -> 24 | H45: =year(D45) -> 2017 | I45: 42925 | J45: =DATEDIF(D45,I45,"D") -> 46 | K45: C | L45: #N/A | P45: Online | Q45: 5762 | R45: 255.28 | S45: 159.42 | T45: =MULTIPLY(Q45,R45) -> 1470923.4 | U45: =MULTIPLY(Q46,S46) -> 589317.33 | V45: =MINUS(T45,U45) -> 881606.03 | W45: =Q45/totals!B$2 -> 0.00087614673 | X45: =W45+X44 -> 0.032485398 | Y45: =T45/totals!B$5 -> 0.00086416659 | Z45: =Z44+Y45 -> 0.024706924 | AA45: =V45/totals!B$4 -> 0.0017579012 | AB45: =AB44+AA45 -> 0.025096409
A46: 5988 | B46: =VLOOKUP($A46,product_category,2, False) -> Vegetables | C46: 127694451 | D46: 40884 | E46: =month(D46) -> 12 | F46: =text(D46,"MMM") -> Dec | G46: =Day(D46) -> 7 | H46: =year(D46) -> 2011 | I46: 40904 | J46: =DATEDIF(D46,I46,"D") -> 20 | K46: L | L46: EST | M46: =VLOOKUP(L46,countries, 2,false) -> Estonia | N46: =VLOOKUP(L46,countries, 4,false) -> Europe | O46: =VLOOKUP(L46,countries, 5,false) -> Northern Europe | P46: Offline | Q46: 6481 | R46: 154.06 | S46: 90.93 | T46: =MULTIPLY(Q46,R46) -> 998462.86 | U46: =MULTIPLY(Q47,S47) -> 62446.08 | V46: =MINUS(T46,U46) -> 936016.78 | W46: =Q46/totals!B$2 -> 0.000985475 | X46: =W46+X45 -> 0.033470873 | Y46: =T46/totals!B$5 -> 0.00058659633 | Z46: =Z45+Y46 -> 0.02529352 | AA46: =V46/totals!B$4 -> 0.0018663949 | AB46: =AB45+AA46 -> 0.026962803
A47: 4594 | B47: =VLOOKUP($A47,product_category,2, False) -> Fruits | C47: 127838218 | D47: 41537 | E47: =month(D47) -> 9 | F47: =text(D47,"MMM") -> Sep | G47: =Day(D47) -> 20 | H47: =year(D47) -> 2013 | I47: 41576 | J47: =DATEDIF(D47,I47,"D") -> 39 | K47: C | L47: NLD | M47: =VLOOKUP(L47,countries, 2,false) -> Netherlands | N47: =VLOOKUP(L47,countries, 4,false) -> Europe | O47: =VLOOKUP(L47,countries, 5,false) -> Western Europe | P47: Offline | Q47: 9024 | R47: 9.33 | S47: 6.92 | T47: =MULTIPLY(Q47,R47) -> 84193.92 | U47: =MULTIPLY(Q48,S48) -> 1262287.6 | V47: =MINUS(T47,U47) -> -1178093.6 | W47: =Q47/totals!B$2 -> 0.0013721534 | X47: =W47+X46 -> 0.034843026 | Y47: =T47/totals!B$5 -> 4.9463877e-05 | Z47: =Z46+Y47 -> 0.025342984 | AA47: =V47/totals!B$4 -> -0.0023490903 | AB47: =AB46+AA47 -> 0.024613713
A48: 7331 | B48: =VLOOKUP($A48,product_category,2, False) -> Baby Food | C48: 128003442 | D48: 40430 | E48: =month(D48) -> 9 | F48: =text(D48,"MMM") -> Sep | G48: =Day(D48) -> 9 | H48: =year(D48) -> 2010 | I48: 40474 | J48: =DATEDIF(D48,I48,"D") -> 44 | K48: L | L48: CHE | M48: =VLOOKUP(L48,countries, 2,false) -> Switzerland | N48: =VLOOKUP(L48,countries, 4,false) -> Europe | O48: =VLOOKUP(L48,countries, 5,false) -> Western Europe | P48: Online | Q48: 7918 | R48: 255.28 | S48: 159.42 | T48: =MULTIPLY(Q48,R48) -> 2021307 | U48: =MULTIPLY(Q49,S49) -> 1589098.6 | V48: =MINUS(T48,U48) -> 432208.48 | W48: =Q48/totals!B$2 -> 0.0012039795 | X48: =W48+X47 -> 0.036047006 | Y48: =T48/totals!B$5 -> 0.0011875167 | Z48: =Z47+Y48 -> 0.026530501 | AA48: =V48/totals!B$4 -> 0.00086181328 | AB48: =AB47+AA48 -> 0.025475526
A49: 7331 | B49: =VLOOKUP($A49,product_category,2, False) -> Baby Food | C49: 128686225 | D49: 40568 | E49: =month(D49) -> 1 | F49: =text(D49,"MMM") -> Jan | G49: =Day(D49) -> 25 | H49: =year(D49) -> 2011 | I49: 40615 | J49: =DATEDIF(D49,I49,"D") -> 47 | K49: M | L49: HUN | M49: =VLOOKUP(L49,countries, 2,false) -> Hungary | N49: =VLOOKUP(L49,countries, 4,false) -> Europe | O49: =VLOOKUP(L49,countries, 5,false) -> Eastern Europe | P49: Online | Q49: 9968 | R49: 255.28 | S49: 159.42 | T49: =MULTIPLY(Q49,R49) -> 2544631 | U49: =MULTIPLY(Q50,S50) -> 1931763.8 | V49: =MINUS(T49,U49) -> 612867.28 | W49: =Q49/totals!B$2 -> 0.0015156943 | X49: =W49+X48 -> 0.0375627 | Y49: =T49/totals!B$5 -> 0.0014949692 | Z49: =Z48+Y49 -> 0.02802547 | AA49: =V49/totals!B$4 -> 0.0012220426 | AB49: =AB48+AA49 -> 0.026697569
A50: 7940 | B50: =VLOOKUP($A50,product_category,2, False) -> Household | C50: 128766906 | D50: 40587 | E50: =month(D50) -> 2 | F50: =text(D50,"MMM") -> Feb | G50: =Day(D50) -> 13 | H50: =year(D50) -> 2011 | I50: 40630 | J50: =DATEDIF(D50,I50,"D") -> 43 | K50: C | L50: #N/A | P50: Offline | Q50: 3844 | R50: 668.27 | S50: 502.54 | T50: =MULTIPLY(Q50,R50) -> 2568829.9 | U50: =MULTIPLY(Q51,S51) -> 272979.2 | V50: =MINUS(T50,U50) -> 2295850.7 | W50: =Q50/totals!B$2 -> 0.0005845033 | X50: =W50+X49 -> 0.038147204 | Y50: =T50/totals!B$5 -> 0.001509186 | Z50: =Z49+Y50 -> 0.029534656 | AA50: =V50/totals!B$4 -> 0.0045778709 | AB50: =AB49+AA50 -> 0.03127544
A51: 8681 | B51: =VLOOKUP($A51,product_category,2, False) -> Office Supplies | C51: 129127395 | D51: 41441 | E51: =month(D51) -> 6 | F51: =text(D51,"MMM") -> Jun | G51: =Day(D51) -> 16 | H51: =year(D51) -> 2013 | I51: 41445 | J51: =DATEDIF(D51,I51,"D") -> 4 | K51: L | L51: LVA | M51: =VLOOKUP(L51,countries, 2,false) -> Latvia | N51: =VLOOKUP(L51,countries, 4,false) -> Europe | O51: =VLOOKUP(L51,countries, 5,false) -> Northern Europe | P51: Online | Q51: 520 | R51: 651.21 | S51: 524.96 | T51: =MULTIPLY(Q51,R51) -> 338629.2 | U51: =MULTIPLY(Q52,S52) -> 90251.81 | V51: =MINUS(T51,U51) -> 248377.39 | W51: =Q51/totals!B$2 -> 7.9069125e-05 | X51: =W51+X50 -> 0.038226273 | Y51: =T51/totals!B$5 -> 0.00019894445 | Z51: =Z50+Y51 -> 0.0297336 | AA51: =V51/totals!B$4 -> 0.00049525852 | AB51: =AB50+AA51 -> 0.031770698
A52: 1270 | B52: =VLOOKUP($A52,product_category,2, False) -> Beverages | C52: 129169023 | D52: 41068 | E52: =month(D52) -> 6 | F52: =text(D52,"MMM") -> Jun | G52: =Day(D52) -> 8 | H52: =year(D52) -> 2012 | I52: 41108 | J52: =DATEDIF(D52,I52,"D") -> 40 | K52: M | L52: #N/A | P52: Offline | Q52: 2839 | R52: 47.45 | S52: 31.79 | T52: =MULTIPLY(Q52,R52) -> 134710.55 | U52: =MULTIPLY(Q53,S53) -> 106256.25 | V52: =MINUS(T52,U52) -> 28454.3 | W52: =Q52/totals!B$2 -> 0.00043168701 | X52: =W52+X51 -> 0.03865796 | Y52: =T52/totals!B$5 -> 7.9142367e-05 | Z52: =Z51+Y52 -> 0.029812743 | AA52: =V52/totals!B$4 -> 5.6737188e-05 | AB52: =AB51+AA52 -> 0.031827436
A53: 3127 | B53: =VLOOKUP($A53,product_category,2, False) -> Personal Care | C53: 129875409 | D53: 40652 | E53: =month(D53) -> 4 | F53: =text(D53,"MMM") -> Apr | G53: =Day(D53) -> 19 | H53: =year(D53) -> 2011 | I53: 40659 | J53: =DATEDIF(D53,I53,"D") -> 7 | K53: L | L53: LTU | M53: =VLOOKUP(L53,countries, 2,false) -> Lithuania | N53: =VLOOKUP(L53,countries, 4,false) -> Europe | O53: =VLOOKUP(L53,countries, 5,false) -> Northern Europe | P53: Offline | Q53: 1875 | R53: 81.73 | S53: 56.67 | T53: =MULTIPLY(Q53,R53) -> 153243.75 | U53: =MULTIPLY(Q54,S54) -> 1005.08 | V53: =MINUS(T53,U53) -> 152238.67 | W53: =Q53/totals!B$2 -> 0.00028510502 | X53: =W53+X52 -> 0.038943065 | Y53: =T53/totals!B$5 -> 9.0030611e-05 | Z53: =Z52+Y53 -> 0.029902773 | AA53: =V53/totals!B$4 -> 0.00030356024 | AB53: =AB52+AA53 -> 0.032130996
A54: 7940 | B54: =VLOOKUP($A54,product_category,2, False) -> Household | C54: 129902875 | D54: 41719 | E54: =month(D54) -> 3 | F54: =text(D54,"MMM") -> Mar | G54: =Day(D54) -> 21 | H54: =year(D54) -> 2014 | I54: 41753 | J54: =DATEDIF(D54,I54,"D") -> 34 | K54: C | L54: BGR | M54: =VLOOKUP(L54,countries, 2,false) -> Bulgaria | N54: =VLOOKUP(L54,countries, 4,false) -> Europe | O54: =VLOOKUP(L54,countries, 5,false) -> Eastern Europe | P54: Online | Q54: 2 | R54: 668.27 | S54: 502.54 | T54: =MULTIPLY(Q54,R54) -> 1336.54 | U54: =MULTIPLY(Q55,S55) -> 396818.52 | V54: =MINUS(T54,U54) -> -395481.98 | W54: =Q54/totals!B$2 -> 3.0411202e-07 | X54: =W54+X53 -> 0.038943369 | Y54: =T54/totals!B$5 -> 7.8521644e-07 | Z54: =Z53+Y54 -> 0.029903558 | AA54: =V54/totals!B$4 -> -0.00078858153 | AB54: =AB53+AA54 -> 0.031342414
A55: 5988 | B55: =VLOOKUP($A55,product_category,2, False) -> Vegetables | C55: 130356919 | D55: 41535 | E55: =month(D55) -> 9 | F55: =text(D55,"MMM") -> Sep | G55: =Day(D55) -> 18 | H55: =year(D55) -> 2013 | I55: 41548 | J55: =DATEDIF(D55,I55,"D") -> 13 | K55: H | L55: CHE | M55: =VLOOKUP(L55,countries, 2,false) -> Switzerland | N55: =VLOOKUP(L55,countries, 4,false) -> Europe | O55: =VLOOKUP(L55,countries, 5,false) -> Western Europe | P55: Online | Q55: 4364 | R55: 154.06 | S55: 90.93 | T55: =MULTIPLY(Q55,R55) -> 672317.84 | U55: =MULTIPLY(Q56,S56) -> 1029971.5 | V55: =MINUS(T55,U55) -> -357653.68 | W55: =Q55/totals!B$2 -> 0.00066357243 | X55: =W55+X54 -> 0.039606941 | Y55: =T55/totals!B$5 -> 0.00039498633 | Z55: =Z54+Y55 -> 0.030298545 | AA55: =V55/totals!B$4 -> -0.00071315281 | AB55: =AB54+AA55 -> 0.030629262
A56: 8681 | B56: =VLOOKUP($A56,product_category,2, False) -> Office Supplies | C56: 130754315 | D56: 41574 | E56: =month(D56) -> 10 | F56: =text(D56,"MMM") -> Oct | G56: =Day(D56) -> 27 | H56: =year(D56) -> 2013 | I56: 41580 | J56: =DATEDIF(D56,I56,"D") -> 6 | K56: H | L56: FRA | M56: =VLOOKUP(L56,countries, 2,false) -> France | N56: =VLOOKUP(L56,countries, 4,false) -> Europe | O56: =VLOOKUP(L56,countries, 5,false) -> Western Europe | P56: Online | Q56: 1962 | R56: 651.21 | S56: 524.96 | T56: =MULTIPLY(Q56,R56) -> 1277674 | U56: =MULTIPLY(Q57,S57) -> 450753.18 | V56: =MINUS(T56,U56) -> 826920.84 | W56: =Q56/totals!B$2 -> 0.00029833389 | X56: =W56+X55 -> 0.039905275 | Y56: =T56/totals!B$5 -> 0.00075063272 | Z56: =Z55+Y56 -> 0.031049177 | AA56: =V56/totals!B$4 -> 0.0016488602 | AB56: =AB55+AA56 -> 0.032278122
A57: 3127 | B57: =VLOOKUP($A57,product_category,2, False) -> Personal Care | C57: 131585586 | D57: 42807 | E57: =month(D57) -> 3 | F57: =text(D57,"MMM") -> Mar | G57: =Day(D57) -> 13 | H57: =year(D57) -> 2017 | I57: 42838 | J57: =DATEDIF(D57,I57,"D") -> 31 | K57: C | L57: FRA | M57: =VLOOKUP(L57,countries, 2,false) -> France | N57: =VLOOKUP(L57,countries, 4,false) -> Europe | O57: =VLOOKUP(L57,countries, 5,false) -> Western Europe | P57: Offline | Q57: 7954 | R57: 81.73 | S57: 56.67 | T57: =MULTIPLY(Q57,R57) -> 650080.42 | U57: =MULTIPLY(Q58,S58) -> 68287.35 | V57: =MINUS(T57,U57) -> 581793.07 | W57: =Q57/totals!B$2 -> 0.0012094535 | X57: =W57+X56 -> 0.041114729 | Y57: =T57/totals!B$5 -> 0.00038192185 | Z57: =Z56+Y57 -> 0.031431099 | AA57: =V57/totals!B$4 -> 0.0011600813 | AB57: =AB56+AA57 -> 0.033438203
A58: 3127 | B58: =VLOOKUP($A58,product_category,2, False) -> Personal Care | C58: 132069671 | D58: 42925 | E58: =month(D58) -> 7 | F58: =text(D58,"MMM") -> Jul | G58: =Day(D58) -> 9 | H58: =year(D58) -> 2017 | I58: 42936 | J58: =DATEDIF(D58,I58,"D") -> 11 | K58: M | L58: AUT | M58: =VLOOKUP(L58,countries, 2,false) -> Austria | N58: =VLOOKUP(L58,countries, 4,false) -> Europe | O58: =VLOOKUP(L58,countries, 5,false) -> Western Europe | P58: Online | Q58: 1205 | R58: 81.73 | S58: 56.67 | T58: =MULTIPLY(Q58,R58) -> 98484.65 | U58: =MULTIPLY(Q59,S59) -> 2419476 | V58: =MINUS(T58,U58) -> -2320991.4 | W58: =Q58/totals!B$2 -> 0.00018322749 | X58: =W58+X57 -> 0.041297956 | Y58: =T58/totals!B$5 -> 5.7859672e-05 | Z58: =Z57+Y58 -> 0.031488959 | AA58: =V58/totals!B$4 -> -0.0046280008 | AB58: =AB57+AA58 -> 0.028810202
A59: 8293 | B59: =VLOOKUP($A59,product_category,2, False) -> Cosmetics | C59: 132603538 | D59: 41172 | E59: =month(D59) -> 9 | F59: =text(D59,"MMM") -> Sep | G59: =Day(D59) -> 20 | H59: =year(D59) -> 2012 | I59: 41219 | J59: =DATEDIF(D59,I59,"D") -> 47 | K59: M | L59: HUN | M59: =VLOOKUP(L59,countries, 2,false) -> Hungary | N59: =VLOOKUP(L59,countries, 4,false) -> Europe | O59: =VLOOKUP(L59,countries, 5,false) -> Eastern Europe | P59: Online | Q59: 9188 | R59: 437.2 | S59: 263.33 | T59: =MULTIPLY(Q59,R59) -> 4016993.6 | U59: =MULTIPLY(Q60,S60) -> 471381.06 | V59: =MINUS(T59,U59) -> 3545612.5 | W59: =Q59/totals!B$2 -> 0.0013970906 | X59: =W59+X58 -> 0.042695047 | Y59: =T59/totals!B$5 -> 0.0023599813 | Z59: =Z58+Y59 -> 0.03384894 | AA59: =V59/totals!B$4 -> 0.0070698659 | AB59: =AB58+AA59 -> 0.035880068
A60: 3127 | B60: =VLOOKUP($A60,product_category,2, False) -> Personal Care | C60: 133276450 | D60: 42396 | E60: =month(D60) -> 1 | F60: =text(D60,"MMM") -> Jan | G60: =Day(D60) -> 27 | H60: =year(D60) -> 2016 | I60: 42444 | J60: =DATEDIF(D60,I60,"D") -> 48 | K60: H | L60: #N/A | P60: Online | Q60: 8318 | R60: 81.73 | S60: 56.67 | T60: =MULTIPLY(Q60,R60) -> 679830.14 | U60: =MULTIPLY(Q61,S61) -> 749808.78 | V60: =MINUS(T60,U60) -> -69978.64 | W60: =Q60/totals!B$2 -> 0.0012648019 | X60: =W60+X59 -> 0.043959849 | Y60: =T60/totals!B$5 -> 0.0003993998 | Z60: =Z59+Y60 -> 0.03424834 | AA60: =V60/totals!B$4 -> -0.00013953572 | AB60: =AB59+AA60 -> 0.035740532
A61: 5988 | B61: =VLOOKUP($A61,product_category,2, False) -> Vegetables | C61: 134121024 | D61: 40602 | E61: =month(D61) -> 2 | F61: =text(D61,"MMM") -> Feb | G61: =Day(D61) -> 28 | H61: =year(D61) -> 2011 | I61: 40641 | J61: =DATEDIF(D61,I61,"D") -> 39 | K61: L | L61: EST | M61: =VLOOKUP(L61,countries, 2,false) -> Estonia | N61: =VLOOKUP(L61,countries, 4,false) -> Europe | O61: =VLOOKUP(L61,countries, 5,false) -> Northern Europe | P61: Online | Q61: 8246 | R61: 154.06 | S61: 90.93 | T61: =MULTIPLY(Q61,R61) -> 1270378.8 | U61: =MULTIPLY(Q62,S62) -> 227942.4 | V61: =MINUS(T61,U61) -> 1042436.4 | W61: =Q61/totals!B$2 -> 0.0012538539 | X61: =W61+X60 -> 0.045213703 | Y61: =T61/totals!B$5 -> 0.00074634675 | Z61: =Z60+Y61 -> 0.034994687 | AA61: =V61/totals!B$4 -> 0.002078593 | AB61: =AB60+AA61 -> 0.037819125
A62: 2455 | B62: =VLOOKUP($A62,product_category,2, False) -> Clothes | C62: 134790503 | D62: 41001 | E62: =month(D62) -> 4 | F62: =text(D62,"MMM") -> Apr | G62: =Day(D62) -> 2 | H62: =year(D62) -> 2012 | I62: 41025 | J62: =DATEDIF(D62,I62,"D") -> 24 | K62: M | L62: ITA | M62: =VLOOKUP(L62,countries, 2,false) -> Italy | N62: =VLOOKUP(L62,countries, 4,false) -> Europe | O62: =VLOOKUP(L62,countries, 5,false) -> Southern Europe | P62: Online | Q62: 6360 | R62: 109.28 | S62: 35.84 | T62: =MULTIPLY(Q62,R62) -> 695020.8 | U62: =MULTIPLY(Q63,S63) -> 286555.06 | V62: =MINUS(T62,U62) -> 408465.74 | W62: =Q62/totals!B$2 -> 0.00096707622 | X62: =W62+X61 -> 0.046180779 | Y62: =T62/totals!B$5 -> 0.0004083243 | Z62: =Z61+Y62 -> 0.035403011 | AA62: =V62/totals!B$4 -> 0.00081447083 | AB62: =AB61+AA62 -> 0.038633596
A63: 1270 | B63: =VLOOKUP($A63,product_category,2, False) -> Beverages | C63: 136624276 | D63: 42420 | E63: =month(D63) -> 2 | F63: =text(D63,"MMM") -> Feb | G63: =Day(D63) -> 20 | H63: =year(D63) -> 2016 | I63: 42437 | J63: =DATEDIF(D63,I63,"D") -> 17 | K63: L | L63: LVA | M63: =VLOOKUP(L63,countries, 2,false) -> Latvia | N63: =VLOOKUP(L63,countries, 4,false) -> Europe | O63: =VLOOKUP(L63,countries, 5,false) -> Northern Europe | P63: Offline | Q63: 9014 | R63: 47.45 | S63: 31.79 | T63: =MULTIPLY(Q63,R63) -> 427714.3 | U63: =MULTIPLY(Q64,S64) -> 343865.76 | V63: =MINUS(T63,U63) -> 83848.54 | W63: =Q63/totals!B$2 -> 0.0013706329 | X63: =W63+X62 -> 0.047551412 | Y63: =T63/totals!B$5 -> 0.00025128189 | Z63: =Z62+Y63 -> 0.035654293 | AA63: =V63/totals!B$4 -> 0.00016719197 | AB63: =AB62+AA63 -> 0.038800788
A64: 8969 | B64: =VLOOKUP($A64,product_category,2, False) -> Snacks | C64: 138025033 | D64: 41468 | E64: =month(D64) -> 7 | F64: =text(D64,"MMM") -> Jul | G64: =Day(D64) -> 13 | H64: =year(D64) -> 2013 | I64: 41489 | J64: =DATEDIF(D64,I64,"D") -> 21 | K64: L | L64: GBR | M64: =VLOOKUP(L64,countries, 2,false) -> United Kingdom | N64: =VLOOKUP(L64,countries, 4,false) -> Europe | O64: =VLOOKUP(L64,countries, 5,false) -> Northern Europe | P64: Online | Q64: 3529 | R64: 152.58 | S64: 97.44 | T64: =MULTIPLY(Q64,R64) -> 538454.82 | U64: =MULTIPLY(Q65,S65) -> 5249.6 | V64: =MINUS(T64,U64) -> 533205.22 | W64: =Q64/totals!B$2 -> 0.00053660566 | X64: =W64+X63 -> 0.048088017 | Y64: =T64/totals!B$5 -> 0.00031634188 | Z64: =Z63+Y64 -> 0.035970635 | AA64: =V64/totals!B$4 -> 0.0010631983 | AB64: =AB63+AA64 -> 0.039863986
A65: 8681 | B65: =VLOOKUP($A65,product_category,2, False) -> Office Supplies | C65: 138182103 | D65: 41860 | E65: =month(D65) -> 8 | F65: =text(D65,"MMM") -> Aug | G65: =Day(D65) -> 9 | H65: =year(D65) -> 2014 | I65: 41867 | J65: =DATEDIF(D65,I65,"D") -> 7 | K65: C | L65: NLD | M65: =VLOOKUP(L65,countries, 2,false) -> Netherlands | N65: =VLOOKUP(L65,countries, 4,false) -> Europe | O65: =VLOOKUP(L65,countries, 5,false) -> Western Europe | P65: Online | Q65: 10 | R65: 651.21 | S65: 524.96 | T65: =MULTIPLY(Q65,R65) -> 6512.1 | U65: =MULTIPLY(Q66,S66) -> 321843.2 | V65: =MINUS(T65,U65) -> -315331.1 | W65: =Q65/totals!B$2 -> 1.5205601e-06 | X65: =W65+X64 -> 0.048089538 | Y65: =T65/totals!B$5 -> 3.8258548e-06 | Z65: =Z64+Y65 -> 0.035974461 | AA65: =V65/totals!B$4 -> -0.00062876261 | AB65: =AB64+AA65 -> 0.039235224
A66: 2455 | B66: =VLOOKUP($A66,product_category,2, False) -> Clothes | C66: 138820683 | D66: 40368 | E66: =month(D66) -> 7 | F66: =text(D66,"MMM") -> Jul | G66: =Day(D66) -> 9 | H66: =year(D66) -> 2010 | I66: 40368 | J66: =DATEDIF(D66,I66,"D") -> 0 | K66: L | L66: RUS | M66: =VLOOKUP(L66,countries, 2,false) -> Russia | N66: =VLOOKUP(L66,countries, 4,false) -> Europe | O66: =VLOOKUP(L66,countries, 5,false) -> Eastern Europe | P66: Offline | Q66: 8980 | R66: 109.28 | S66: 35.84 | T66: =MULTIPLY(Q66,R66) -> 981334.4 | U66: =MULTIPLY(Q67,S67) -> 427911.25 | V66: =MINUS(T66,U66) -> 553423.15 | W66: =Q66/totals!B$2 -> 0.001365463 | X66: =W66+X65 -> 0.049455001 | Y66: =T66/totals!B$5 -> 0.00057653337 | Z66: =Z65+Y66 -> 0.036550994 | AA66: =V66/totals!B$4 -> 0.0011035124 | AB66: =AB65+AA66 -> 0.040338736
A67: 8293 | B67: =VLOOKUP($A67,product_category,2, False) -> Cosmetics | C67: 139201343 | D67: 42609 | E67: =month(D67) -> 8 | F67: =text(D67,"MMM") -> Aug | G67: =Day(D67) -> 27 | H67: =year(D67) -> 2016 | I67: 42619 | J67: =DATEDIF(D67,I67,"D") -> 10 | K67: H | L67: IRL | M67: =VLOOKUP(L67,countries, 2,false) -> Ireland | N67: =VLOOKUP(L67,countries, 4,false) -> Europe | O67: =VLOOKUP(L67,countries, 5,false) -> Northern Europe | P67: Offline | Q67: 1625 | R67: 437.2 | S67: 263.33 | T67: =MULTIPLY(Q67,R67) -> 710450 | U67: =MULTIPLY(Q68,S68) -> 270971.4 | V67: =MINUS(T67,U67) -> 439478.6 | W67: =Q67/totals!B$2 -> 0.00024709102 | X67: =W67+X66 -> 0.049702092 | Y67: =T67/totals!B$5 -> 0.00041738895 | Z67: =Z66+Y67 -> 0.036968383 | AA67: =V67/totals!B$4 -> 0.00087630973 | AB67: =AB66+AA67 -> 0.041215046
A68: 5988 | B68: =VLOOKUP($A68,product_category,2, False) -> Vegetables | C68: 139949357 | D68: 41821 | E68: =month(D68) -> 7 | F68: =text(D68,"MMM") -> Jul | G68: =Day(D68) -> 1 | H68: =year(D68) -> 2014 | I68: 41834 | J68: =DATEDIF(D68,I68,"D") -> 13 | K68: H | L68: #N/A | P68: Online | Q68: 2980 | R68: 154.06 | S68: 90.93 | T68: =MULTIPLY(Q68,R68) -> 459098.8 | U68: =MULTIPLY(Q69,S69) -> 1214741.3 | V68: =MINUS(T68,U68) -> -755642.49 | W68: =Q68/totals!B$2 -> 0.00045312691 | X68: =W68+X67 -> 0.050155219 | Y68: =T68/totals!B$5 -> 0.00026972027 | Z68: =Z67+Y68 -> 0.037238103 | AA68: =V68/totals!B$4 -> -0.0015067329 | AB68: =AB67+AA68 -> 0.039708313
A69: 8293 | B69: =VLOOKUP($A69,product_category,2, False) -> Cosmetics | C69: 140461766 | D69: 41828 | E69: =month(D69) -> 7 | F69: =text(D69,"MMM") -> Jul | G69: =Day(D69) -> 8 | H69: =year(D69) -> 2014 | I69: 41840 | J69: =DATEDIF(D69,I69,"D") -> 12 | K69: C | L69: UKR | M69: =VLOOKUP(L69,countries, 2,false) -> Ukraine | N69: =VLOOKUP(L69,countries, 4,false) -> Europe | O69: =VLOOKUP(L69,countries, 5,false) -> Eastern Europe | P69: Online | Q69: 4613 | R69: 437.2 | S69: 263.33 | T69: =MULTIPLY(Q69,R69) -> 2016803.6 | U69: =MULTIPLY(Q70,S70) -> 335203.05 | V69: =MINUS(T69,U69) -> 1681600.6 | W69: =Q69/totals!B$2 -> 0.00070143437 | X69: =W69+X68 -> 0.050856653 | Y69: =T69/totals!B$5 -> 0.0011848709 | Z69: =Z68+Y69 -> 0.038422974 | AA69: =V69/totals!B$4 -> 0.0033530709 | AB69: =AB68+AA69 -> 0.043061384
A70: 3127 | B70: =VLOOKUP($A70,product_category,2, False) -> Personal Care | C70: 140499961 | D70: 40631 | E70: =month(D70) -> 3 | F70: =text(D70,"MMM") -> Mar | G70: =Day(D70) -> 29 | H70: =year(D70) -> 2011 | I70: 40663 | J70: =DATEDIF(D70,I70,"D") -> 32 | K70: L | L70: LVA | M70: =VLOOKUP(L70,countries, 2,false) -> Latvia | N70: =VLOOKUP(L70,countries, 4,false) -> Europe | O70: =VLOOKUP(L70,countries, 5,false) -> Northern Europe | P70: Online | Q70: 5915 | R70: 81.73 | S70: 56.67 | T70: =MULTIPLY(Q70,R70) -> 483432.95 | U70: =MULTIPLY(Q71,S71) -> 7333.32 | V70: =MINUS(T70,U70) -> 476099.63 | W70: =Q70/totals!B$2 -> 0.0008994113 | X70: =W70+X69 -> 0.051756064 | Y70: =T70/totals!B$5 -> 0.00028401657 | Z70: =Z69+Y70 -> 0.038706991 | AA70: =V70/totals!B$4 -> 0.00094933118 | AB70: =AB69+AA70 -> 0.044010715
A71: 7331 | B71: =VLOOKUP($A71,product_category,2, False) -> Baby Food | C71: 141764247 | D71: 41470 | E71: =month(D71) -> 7 | F71: =text(D71,"MMM") -> Jul | G71: =Day(D71) -> 15 | H71: =year(D71) -> 2013 | I71: 41515 | J71: =DATEDIF(D71,I71,"D") -> 45 | K71: H | L71: AND | M71: =VLOOKUP(L71,countries, 2,false) -> Andorra | N71: =VLOOKUP(L71,countries, 4,false) -> Europe | O71: =VLOOKUP(L71,countries, 5,false) -> Southern Europe | P71: Offline | Q71: 46 | R71: 255.28 | S71: 159.42 | T71: =MULTIPLY(Q71,R71) -> 11742.88 | U71: =MULTIPLY(Q72,S72) -> 154183.68 | V71: =MINUS(T71,U71) -> -142440.8 | W71: =Q71/totals!B$2 -> 6.9945765e-06 | X71: =W71+X70 -> 0.051763059 | Y71: =T71/totals!B$5 -> 6.8989349e-06 | Z71: =Z70+Y71 -> 0.03871389 | AA71: =V71/totals!B$4 -> -0.00028402352 | AB71: =AB70+AA71 -> 0.043726692
A72: 2455 | B72: =VLOOKUP($A72,product_category,2, False) -> Clothes | C72: 141846215 | D72: 41108 | E72: =month(D72) -> 7 | F72: =text(D72,"MMM") -> Jul | G72: =Day(D72) -> 18 | H72: =year(D72) -> 2012 | I72: 41137 | J72: =DATEDIF(D72,I72,"D") -> 29 | K72: H | L72: GEO | M72: =VLOOKUP(L72,countries, 2,false) -> Georgia | N72: =VLOOKUP(L72,countries, 4,false) -> Asia | O72: =VLOOKUP(L72,countries, 5,false) -> Western Asia | P72: Online | Q72: 4302 | R72: 109.28 | S72: 35.84 | T72: =MULTIPLY(Q72,R72) -> 470122.56 | U72: =MULTIPLY(Q73,S73) -> 1540285.1 | V72: =MINUS(T72,U72) -> -1070162.5 | W72: =Q72/totals!B$2 -> 0.00065414496 | X72: =W72+X71 -> 0.052417204 | Y72: =T72/totals!B$5 -> 0.00027619672 | Z72: =Z71+Y72 -> 0.038990086 | AA72: =V72/totals!B$4 -> -0.0021338783 | AB72: =AB71+AA72 -> 0.041592813
A73: 7940 | B73: =VLOOKUP($A73,product_category,2, False) -> Household | C73: 141875827 | D73: 40615 | E73: =month(D73) -> 3 | F73: =text(D73,"MMM") -> Mar | G73: =Day(D73) -> 13 | H73: =year(D73) -> 2011 | I73: 40649 | J73: =DATEDIF(D73,I73,"D") -> 34 | K73: C | L73: POL | M73: =VLOOKUP(L73,countries, 2,false) -> Poland | N73: =VLOOKUP(L73,countries, 4,false) -> Europe | O73: =VLOOKUP(L73,countries, 5,false) -> Eastern Europe | P73: Online | Q73: 3065 | R73: 668.27 | S73: 502.54 | T73: =MULTIPLY(Q73,R73) -> 2048247.6 | U73: =MULTIPLY(Q74,S74) -> 6144.96 | V73: =MINUS(T73,U73) -> 2042102.6 | W73: =Q73/totals!B$2 -> 0.00046605167 | X73: =W73+X72 -> 0.052883256 | Y73: =T73/totals!B$5 -> 0.0012033442 | Z73: =Z72+Y73 -> 0.040193431 | AA73: =V73/totals!B$4 -> 0.0040719033 | AB73: =AB72+AA73 -> 0.045664717
A74: 4594 | B74: =VLOOKUP($A74,product_category,2, False) -> Fruits | C74: 142375361 | D74: 41678 | E74: =month(D74) -> 2 | F74: =text(D74,"MMM") -> Feb | G74: =Day(D74) -> 8 | H74: =year(D74) -> 2014 | I74: 41689 | J74: =DATEDIF(D74,I74,"D") -> 11 | K74: L | L74: LIE | M74: =VLOOKUP(L74,countries, 2,false) -> Liechtenstein | N74: =VLOOKUP(L74,countries, 4,false) -> Europe | O74: =VLOOKUP(L74,countries, 5,false) -> Western Europe | P74: Online | Q74: 888 | R74: 9.33 | S74: 6.92 | T74: =MULTIPLY(Q74,R74) -> 8285.04 | U74: =MULTIPLY(Q75,S75) -> 1061364.5 | V74: =MINUS(T74,U74) -> -1053079.4 | W74: =Q74/totals!B$2 -> 0.00013502574 | X74: =W74+X73 -> 0.053018281 | Y74: =T74/totals!B$5 -> 4.867456e-06 | Z74: =Z73+Y74 -> 0.040198298 | AA74: =V74/totals!B$4 -> -0.002099815 | AB74: =AB73+AA74 -> 0.043564902
A75: 7940 | B75: =VLOOKUP($A75,product_category,2, False) -> Household | C75: 142987763 | D75: 41504 | E75: =month(D75) -> 8 | F75: =text(D75,"MMM") -> Aug | G75: =Day(D75) -> 18 | H75: =year(D75) -> 2013 | I75: 41518 | J75: =DATEDIF(D75,I75,"D") -> 14 | K75: L | L75: NLD | M75: =VLOOKUP(L75,countries, 2,false) -> Netherlands | N75: =VLOOKUP(L75,countries, 4,false) -> Europe | O75: =VLOOKUP(L75,countries, 5,false) -> Western Europe | P75: Offline | Q75: 2112 | R75: 668.27 | S75: 502.54 | T75: =MULTIPLY(Q75,R75) -> 1411386.2 | U75: =MULTIPLY(Q76,S76) -> 4258021.4 | V75: =MINUS(T75,U75) -> -2846635.2 | W75: =Q75/totals!B$2 -> 0.00032114229 | X75: =W75+X74 -> 0.053339424 | Y75: =T75/totals!B$5 -> 0.00082918856 | Z75: =Z74+Y75 -> 0.041027487 | AA75: =V75/totals!B$4 -> -0.0056761219 | AB75: =AB74+AA75 -> 0.03788878
A76: 7940 | B76: =VLOOKUP($A76,product_category,2, False) -> Household | C76: 143414771 | D76: 41050 | E76: =month(D76) -> 5 | F76: =text(D76,"MMM") -> May | G76: =Day(D76) -> 21 | H76: =year(D76) -> 2012 | I76: 41063 | J76: =DATEDIF(D76,I76,"D") -> 13 | K76: H | L76: IRL | M76: =VLOOKUP(L76,countries, 2,false) -> Ireland | N76: =VLOOKUP(L76,countries, 4,false) -> Europe | O76: =VLOOKUP(L76,countries, 5,false) -> Northern Europe | P76: Offline | Q76: 8473 | R76: 668.27 | S76: 502.54 | T76: =MULTIPLY(Q76,R76) -> 5662251.7 | U76: =MULTIPLY(Q77,S77) -> 630754.46 | V76: =MINUS(T76,U76) -> 5031497.2 | W76: =Q76/totals!B$2 -> 0.0012883706 | X76: =W76+X75 -> 0.054627794 | Y76: =T76/totals!B$5 -> 0.0033265695 | Z76: =Z75+Y76 -> 0.044354056 | AA76: =V76/totals!B$4 -> 0.010032684 | AB76: =AB75+AA76 -> 0.047921464
A77: 2103 | B77: =VLOOKUP($A77,product_category,2, False) -> Cereal | C77: 144282948 | D77: 41468 | E77: =month(D77) -> 7 | F77: =text(D77,"MMM") -> Jul | G77: =Day(D77) -> 13 | H77: =year(D77) -> 2013 | I77: 41487 | J77: =DATEDIF(D77,I77,"D") -> 19 | K77: H | L77: FIN | M77: =VLOOKUP(L77,countries, 2,false) -> Finland | N77: =VLOOKUP(L77,countries, 4,false) -> Europe | O77: =VLOOKUP(L77,countries, 5,false) -> Northern Europe | P77: Online | Q77: 5386 | R77: 205.7 | S77: 117.11 | T77: =MULTIPLY(Q77,R77) -> 1107900.2 | U77: =MULTIPLY(Q78,S78) -> 243115.5 | V77: =MINUS(T77,U77) -> 864784.7 | W77: =Q77/totals!B$2 -> 0.00081897367 | X77: =W77+X76 -> 0.055446768 | Y77: =T77/totals!B$5 -> 0.0006508907 | Z77: =Z76+Y77 -> 0.045004947 | AA77: =V77/totals!B$4 -> 0.0017243598 | AB77: =AB76+AA77 -> 0.049645824
A78: 7331 | B78: =VLOOKUP($A78,product_category,2, False) -> Baby Food | C78: 144743001 | D78: 41345 | E78: =month(D78) -> 3 | F78: =text(D78,"MMM") -> Mar | G78: =Day(D78) -> 12 | H78: =year(D78) -> 2013 | I78: 41385 | J78: =DATEDIF(D78,I78,"D") -> 40 | K78: M | L78: SVN | M78: =VLOOKUP(L78,countries, 2,false) -> Slovenia | N78: =VLOOKUP(L78,countries, 4,false) -> Europe | O78: =VLOOKUP(L78,countries, 5,false) -> Southern Europe | P78: Offline | Q78: 1525 | R78: 255.28 | S78: 159.42 | T78: =MULTIPLY(Q78,R78) -> 389302 | U78: =MULTIPLY(Q79,S79) -> 654100.16 | V78: =MINUS(T78,U78) -> -264798.16 | W78: =Q78/totals!B$2 -> 0.00023188542 | X78: =W78+X77 -> 0.055678653 | Y78: =T78/totals!B$5 -> 0.00022871469 | Z78: =Z77+Y78 -> 0.045233662 | AA78: =V78/totals!B$4 -> -0.00052800114 | AB78: =AB77+AA78 -> 0.049117823
A79: 8681 | B79: =VLOOKUP($A79,product_category,2, False) -> Office Supplies | C79: 144978606 | D79: 40549 | E79: =month(D79) -> 1 | F79: =text(D79,"MMM") -> Jan | G79: =Day(D79) -> 6 | H79: =year(D79) -> 2011 | I79: 40593 | J79: =DATEDIF(D79,I79,"D") -> 44 | K79: C | L79: IRL | M79: =VLOOKUP(L79,countries, 2,false) -> Ireland | N79: =VLOOKUP(L79,countries, 4,false) -> Europe | O79: =VLOOKUP(L79,countries, 5,false) -> Northern Europe | P79: Online | Q79: 1246 | R79: 651.21 | S79: 524.96 | T79: =MULTIPLY(Q79,R79) -> 811407.66 | U79: =MULTIPLY(Q80,S80) -> 636419.07 | V79: =MINUS(T79,U79) -> 174988.59 | W79: =Q79/totals!B$2 -> 0.00018946179 | X79: =W79+X78 -> 0.055868115 | Y79: =T79/totals!B$5 -> 0.00047670151 | Z79: =Z78+Y79 -> 0.045710363 | AA79: =V79/totals!B$4 -> 0.00034892303 | AB79: =AB78+AA79 -> 0.049466746
A80: 5988 | B80: =VLOOKUP($A80,product_category,2, False) -> Vegetables | C80: 146349751 | D80: 42856 | E80: =month(D80) -> 5 | F80: =text(D80,"MMM") -> May | G80: =Day(D80) -> 1 | H80: =year(D80) -> 2017 | I80: 42899 | J80: =DATEDIF(D80,I80,"D") -> 43 | K80: M | L80: LTU | M80: =VLOOKUP(L80,countries, 2,false) -> Lithuania | N80: =VLOOKUP(L80,countries, 4,false) -> Europe | O80: =VLOOKUP(L80,countries, 5,false) -> Northern Europe | P80: Online | Q80: 6999 | R80: 154.06 | S80: 90.93 | T80: =MULTIPLY(Q80,R80) -> 1078265.9 | U80: =MULTIPLY(Q81,S81) -> 1326129.9 | V80: =MINUS(T80,U80) -> -247863.94 | W80: =Q80/totals!B$2 -> 0.00106424 | X80: =W80+X79 -> 0.056932355 | Y80: =T80/totals!B$5 -> 0.00063348059 | Z80: =Z79+Y80 -> 0.046343844 | AA80: =V80/totals!B$4 -> -0.00049423472 | AB80: =AB79+AA80 -> 0.048972511
... A84: 7940 | B84: =VLOOKUP($A84,product_category,2, False) -> Household | C84: 149274003 | D84: 41393 | E84: =month(D84) -> 4 | F84: =text(D84,"MMM") -> Apr | G84: =Day(D84) -> 29 | H84: =year(D84) -> 2013 | I84: 41423 | J84: =DATEDIF(D84,I84,"D") -> 30 | K84: C | L84: NOR | M84: =VLOOKUP(L84,countries, 2,false) -> Norway | N84: =VLOOKUP(L84,countries, 4,false) -> Europe | O84: =VLOOKUP(L84,countries, 5,false) -> Northern Europe | P84: Offline | Q84: 2350 | R84: 668.27 | S84: 502.54 | T84: =MULTIPLY(Q84,R84) -> 1570434.5 | U84: =MULTIPLY(Q85,S85) -> 2081466.4 | V84: =MINUS(T84,U84) -> -511031.9 | W84: =Q84/totals!B$2 -> 0.00035733162 | X84: =W84+X83 -> 0.058694684 | Y84: =T84/totals!B$5 -> 0.00092262932 | Z84: =Z83+Y84 -> 0.049650498 | AA84: =V84/totals!B$4 -> -0.0010189853 | AB84: =AB83+AA84 -> 0.051438341
A85: 8681 | B85: =VLOOKUP($A85,product_category,2, False) -> Office Supplies | C85: 150293242 | D85: 42143 | E85: =month(D85) -> 5 | F85: =text(D85,"MMM") -> May | G85: =Day(D85) -> 19 | H85: =year(D85) -> 2015 | I85: 42176 | J85: =DATEDIF(D85,I85,"D") -> 33 | K85: H | L85: #N/A | P85: Offline | Q85: 3965 | R85: 651.21 | S85: 524.96 | T85: =MULTIPLY(Q85,R85) -> 2582047.6 | U85: =MULTIPLY(Q86,S86) -> 1469644.7 | V85: =MINUS(T85,U85) -> 1112402.9 | W85: =Q85/totals!B$2 -> 0.00060290208 | X85: =W85+X84 -> 0.059297586 | Y85: =T85/totals!B$5 -> 0.0015169514 | Z85: =Z84+Y85 -> 0.051167449 | AA85: =V85/totals!B$4 -> 0.0022181046 | AB85: =AB84+AA85 -> 0.053656446
A86: 8293 | B86: =VLOOKUP($A86,product_category,2, False) -> Cosmetics | C86: 151312482 | D86: 42892 | E86: =month(D86) -> 6 | F86: =text(D86,"MMM") -> Jun | G86: =Day(D86) -> 6 | H86: =year(D86) -> 2017 | I86: 42928 | J86: =DATEDIF(D86,I86,"D") -> 36 | K86: H | L86: CZE | M86: =VLOOKUP(L86,countries, 2,false) -> Czech Republic | N86: =VLOOKUP(L86,countries, 4,false) -> Europe | O86: =VLOOKUP(L86,countries, 5,false) -> Eastern Europe | P86: Online | Q86: 5581 | R86: 437.2 | S86: 263.33 | T86: =MULTIPLY(Q86,R86) -> 2440013.2 | U86: =MULTIPLY(Q87,S87) -> 903751.98 | V86: =MINUS(T86,U86) -> 1536261.2 | W86: =Q86/totals!B$2 -> 0.00084862459 | X86: =W86+X85 -> 0.060146211 | Y86: =T86/totals!B$5 -> 0.0014335063 | Z86: =Z85+Y86 -> 0.052600956 | AA86: =V86/totals!B$4 -> 0.0030632678 | AB86: =AB85+AA86 -> 0.056719714
A87: 7331 | B87: =VLOOKUP($A87,product_category,2, False) -> Baby Food | C87: 152191388 | D87: 41047 | E87: =month(D87) -> 5 | F87: =text(D87,"MMM") -> May | G87: =Day(D87) -> 18 | H87: =year(D87) -> 2012 | I87: 41082 | J87: =DATEDIF(D87,I87,"D") -> 35 | K87: L | L87: ALB | M87: =VLOOKUP(L87,countries, 2,false) -> Albania | N87: =VLOOKUP(L87,countries, 4,false) -> Europe | O87: =VLOOKUP(L87,countries, 5,false) -> Southern Europe | P87: Offline | Q87: 5669 | R87: 255.28 | S87: 159.42 | T87: =MULTIPLY(Q87,R87) -> 1447182.3 | U87: =MULTIPLY(Q88,S88) -> 252000.79 | V87: =MINUS(T87,U87) -> 1195181.5 | W87: =Q87/totals!B$2 -> 0.00086200552 | X87: =W87+X86 -> 0.061008216 | Y87: =T87/totals!B$5 -> 0.00085021874 | Z87: =Z86+Y87 -> 0.053451174 | AA87: =V87/totals!B$4 -> 0.0023831631 | AB87: =AB86+AA87 -> 0.059102877
A88: 8875 | B88: =VLOOKUP($A88,product_category,2, False) -> Meat | C88: 152411115 | D88: 41278 | E88: =month(D88) -> 1 | F88: =text(D88,"MMM") -> Jan | G88: =Day(D88) -> 4 | H88: =year(D88) -> 2013 | I88: 41326 | J88: =DATEDIF(D88,I88,"D") -> 48 | K88: H | L88: SWE | M88: =VLOOKUP(L88,countries, 2,false) -> Sweden | N88: =VLOOKUP(L88,countries, 4,false) -> Europe | O88: =VLOOKUP(L88,countries, 5,false) -> Northern Europe | P88: Online | Q88: 691 | R88: 421.89 | S88: 364.69 | T88: =MULTIPLY(Q88,R88) -> 291525.99 | U88: =MULTIPLY(Q89,S89) -> 304747.52 | V88: =MINUS(T88,U88) -> -13221.53 | W88: =Q88/totals!B$2 -> 0.0001050707 | X88: =W88+X87 -> 0.061113287 | Y88: =T88/totals!B$5 -> 0.00017127134 | Z88: =Z87+Y88 -> 0.053622446 | AA88: =V88/totals!B$4 -> -2.6363412e-05 | AB88: =AB87+AA88 -> 0.059076514
A89: 2455 | B89: =VLOOKUP($A89,product_category,2, False) -> Clothes | C89: 152505099 | D89: 41036 | E89: =month(D89) -> 5 | F89: =text(D89,"MMM") -> May | G89: =Day(D89) -> 7 | H89: =year(D89) -> 2012 | I89: 41048 | J89: =DATEDIF(D89,I89,"D") -> 12 | K89: M | L89: SMR | M89: =VLOOKUP(L89,countries, 2,false) -> San Marino | N89: =VLOOKUP(L89,countries, 4,false) -> Europe | O89: =VLOOKUP(L89,countries, 5,false) -> Southern Europe | P89: Offline | Q89: 8503 | R89: 109.28 | S89: 35.84 | T89: =MULTIPLY(Q89,R89) -> 929207.84 | U89: =MULTIPLY(Q90,S90) -> 1049.92 | V89: =MINUS(T89,U89) -> 928157.92 | W89: =Q89/totals!B$2 -> 0.0012929323 | X89: =W89+X88 -> 0.062406219 | Y89: =T89/totals!B$5 -> 0.00054590905 | Z89: =Z88+Y89 -> 0.054168355 | AA89: =V89/totals!B$4 -> 0.0018507245 | AB89: =AB88+AA89 -> 0.060927238
A90: 8681 | B90: =VLOOKUP($A90,product_category,2, False) -> Office Supplies | C90: 152746713 | D90: 40300 | E90: =month(D90) -> 5 | F90: =text(D90,"MMM") -> May | G90: =Day(D90) -> 2 | H90: =year(D90) -> 2010 | I90: 40306 | J90: =DATEDIF(D90,I90,"D") -> 6 | K90: C | L90: BIH | M90: =VLOOKUP(L90,countries, 2,false) -> Bosnia and Herzegovina | N90: =VLOOKUP(L90,countries, 4,false) -> Europe | O90: =VLOOKUP(L90,countries, 5,false) -> Southern Europe | P90: Offline | Q90: 2 | R90: 651.21 | S90: 524.96 | T90: =MULTIPLY(Q90,R90) -> 1302.42 | U90: =MULTIPLY(Q91,S91) -> 23970.88 | V90: =MINUS(T90,U90) -> -22668.46 | W90: =Q90/totals!B$2 -> 3.0411202e-07 | X90: =W90+X89 -> 0.062406524 | Y90: =T90/totals!B$5 -> 7.6517096e-07 | Z90: =Z89+Y90 -> 0.05416912 | AA90: =V90/totals!B$4 -> -4.5200362e-05 | AB90: =AB89+AA90 -> 0.060882038
A91: 4594 | B91: =VLOOKUP($A91,product_category,2, False) -> Fruits | C91: 153974950 | D91: 40777 | E91: =month(D91) -> 8 | F91: =text(D91,"MMM") -> Aug | G91: =Day(D91) -> 22 | H91: =year(D91) -> 2011 | I91: 40806 | J91: =DATEDIF(D91,I91,"D") -> 29 | K91: L | L91: SWE | M91: =VLOOKUP(L91,countries, 2,false) -> Sweden | N91: =VLOOKUP(L91,countries, 4,false) -> Europe | O91: =VLOOKUP(L91,countries, 5,false) -> Northern Europe | P91: Offline | Q91: 3464 | R91: 9.33 | S91: 6.92 | T91: =MULTIPLY(Q91,R91) -> 32319.12 | U91: =MULTIPLY(Q92,S92) -> 661221.63 | V91: =MINUS(T91,U91) -> -628902.51 | W91: =Q91/totals!B$2 -> 0.00052672202 | X91: =W91+X90 -> 0.062933246 | Y91: =T91/totals!B$5 -> 1.8987463e-05 | Z91: =Z90+Y91 -> 0.054188107 | AA91: =V91/totals!B$4 -> -0.0012540164 | AB91: =AB90+AA91 -> 0.059628021
A92: 8293 | B92: =VLOOKUP($A92,product_category,2, False) -> Cosmetics | C92: 155086886 | D92: 41667 | E92: =month(D92) -> 1 | F92: =text(D92,"MMM") -> Jan | G92: =Day(D92) -> 28 | H92: =year(D92) -> 2014 | I92: 41675 | J92: =DATEDIF(D92,I92,"D") -> 8 | K92: M | L92: SVN | M92: =VLOOKUP(L92,countries, 2,false) -> Slovenia | N92: =VLOOKUP(L92,countries, 4,false) -> Europe | O92: =VLOOKUP(L92,countries, 5,false) -> Southern Europe | P92: Offline | Q92: 2511 | R92: 437.2 | S92: 263.33 | T92: =MULTIPLY(Q92,R92) -> 1097809.2 | U92: =MULTIPLY(Q93,S93) -> 51803.12 | V92: =MINUS(T92,U92) -> 1046006.1 | W92: =Q92/totals!B$2 -> 0.00038181264 | X92: =W92+X91 -> 0.063315058 | Y92: =T92/totals!B$5 -> 0.00064496224 | Z92: =Z91+Y92 -> 0.05483307 | AA92: =V92/totals!B$4 -> 0.0020857109 | AB92: =AB91+AA92 -> 0.061713732
A93: 4594 | B93: =VLOOKUP($A93,product_category,2, False) -> Fruits | C93: 155914723 | D93: 42075 | E93: =month(D93) -> 3 | F93: =text(D93,"MMM") -> Mar | G93: =Day(D93) -> 12 | H93: =year(D93) -> 2015 | I93: 42092 | J93: =DATEDIF(D93,I93,"D") -> 17 | K93: H | L93: IRL | M93: =VLOOKUP(L93,countries, 2,false) -> Ireland | N93: =VLOOKUP(L93,countries, 4,false) -> Europe | O93: =VLOOKUP(L93,countries, 5,false) -> Northern Europe | P93: Offline | Q93: 7486 | R93: 9.33 | S93: 6.92 | T93: =MULTIPLY(Q93,R93) -> 69844.38 | U93: =MULTIPLY(Q94,S94) -> 344780.8 | V93: =MINUS(T93,U93) -> -274936.42 | W93: =Q93/totals!B$2 -> 0.0011382913 | X93: =W93+X92 -> 0.06445335 | Y93: =T93/totals!B$5 -> 4.1033531e-05 | Z93: =Z92+Y93 -> 0.054874103 | AA93: =V93/totals!B$4 -> -0.00054821659 | AB93: =AB92+AA93 -> 0.061165516
A94: 2455 | B94: =VLOOKUP($A94,product_category,2, False) -> Clothes | C94: 156158483 | D94: 42547 | E94: =month(D94) -> 6 | F94: =text(D94,"MMM") -> Jun | G94: =Day(D94) -> 26 | H94: =year(D94) -> 2016 | I94: 42587 | J94: =DATEDIF(D94,I94,"D") -> 40 | K94: C | L94: LTU | M94: =VLOOKUP(L94,countries, 2,false) -> Lithuania | N94: =VLOOKUP(L94,countries, 4,false) -> Europe | O94: =VLOOKUP(L94,countries, 5,false) -> Northern Europe | P94: Offline | Q94: 9620 | R94: 109.28 | S94: 35.84 | T94: =MULTIPLY(Q94,R94) -> 1051273.6 | U94: =MULTIPLY(Q95,S95) -> 1042925.6 | V94: =MINUS(T94,U94) -> 8347.96 | W94: =Q94/totals!B$2 -> 0.0014627788 | X94: =W94+X93 -> 0.065916128 | Y94: =T94/totals!B$5 -> 0.00061762261 | Z94: =Z93+Y94 -> 0.055491726 | AA94: =V94/totals!B$4 -> 1.6645631e-05 | AB94: =AB93+AA94 -> 0.061182161
A95: 7331 | B95: =VLOOKUP($A95,product_category,2, False) -> Baby Food | C95: 158479773 | D95: 42143 | E95: =month(D95) -> 5 | F95: =text(D95,"MMM") -> May | G95: =Day(D95) -> 19 | H95: =year(D95) -> 2015 | I95: 42173 | J95: =DATEDIF(D95,I95,"D") -> 30 | K95: L | L95: RUS | M95: =VLOOKUP(L95,countries, 2,false) -> Russia | N95: =VLOOKUP(L95,countries, 4,false) -> Europe | O95: =VLOOKUP(L95,countries, 5,false) -> Eastern Europe | P95: Offline | Q95: 6542 | R95: 255.28 | S95: 159.42 | T95: =MULTIPLY(Q95,R95) -> 1670041.8 | U95: =MULTIPLY(Q96,S96) -> 384303.36 | V95: =MINUS(T95,U95) -> 1285738.4 | W95: =Q95/totals!B$2 -> 0.00099475042 | X95: =W95+X94 -> 0.066910879 | Y95: =T95/totals!B$5 -> 0.00098114853 | Z95: =Z94+Y95 -> 0.056472874 | AA95: =V95/totals!B$4 -> 0.0025637314 | AB95: =AB94+AA95 -> 0.063745893
A96: 8969 | B96: =VLOOKUP($A96,product_category,2, False) -> Snacks | C96: 158673751 | D96: 41720 | E96: =month(D96) -> 3 | F96: =text(D96,"MMM") -> Mar | G96: =Day(D96) -> 22 | H96: =year(D96) -> 2014 | I96: 41769 | J96: =DATEDIF(D96,I96,"D") -> 49 | K96: H | L96: DEU | M96: =VLOOKUP(L96,countries, 2,false) -> Germany | N96: =VLOOKUP(L96,countries, 4,false) -> Europe | O96: =VLOOKUP(L96,countries, 5,false) -> Western Europe | P96: Online | Q96: 3944 | R96: 152.58 | S96: 97.44 | T96: =MULTIPLY(Q96,R96) -> 601775.52 | U96: =MULTIPLY(Q97,S97) -> 64307.56 | V96: =MINUS(T96,U96) -> 537467.96 | W96: =Q96/totals!B$2 -> 0.0005997089 | X96: =W96+X95 -> 0.067510588 | Y96: =T96/totals!B$5 -> 0.00035354275 | Z96: =Z95+Y96 -> 0.056826417 | AA96: =V96/totals!B$4 -> 0.0010716981 | AB96: =AB95+AA96 -> 0.064817591
A97: 4594 | B97: =VLOOKUP($A97,product_category,2, False) -> Fruits | C97: 159232509 | D97: 41798 | E97: =month(D97) -> 6 | F97: =text(D97,"MMM") -> Jun | G97: =Day(D97) -> 8 | H97: =year(D97) -> 2014 | I97: 41834 | J97: =DATEDIF(D97,I97,"D") -> 36 | K97: H | L97: CHE | M97: =VLOOKUP(L97,countries, 2,false) -> Switzerland | N97: =VLOOKUP(L97,countries, 4,false) -> Europe | O97: =VLOOKUP(L97,countries, 5,false) -> Western Europe | P97: Online | Q97: 9293 | R97: 9.33 | S97: 6.92 | T97: =MULTIPLY(Q97,R97) -> 86703.69 | U97: =MULTIPLY(Q98,S98) -> 3267257.7 | V97: =MINUS(T97,U97) -> -3180554 | W97: =Q97/totals!B$2 -> 0.0014130565 | X97: =W97+X96 -> 0.068923644 | Y97: =T97/totals!B$5 -> 5.0938366e-05 | Z97: =Z96+Y97 -> 0.056877355 | AA97: =V97/totals!B$4 -> -0.006341948 | AB97: =AB96+AA97 -> 0.058475643
A98: 8875 | B98: =VLOOKUP($A98,product_category,2, False) -> Meat | C98: 159805858 | D98: 41232 | E98: =month(D98) -> 11 | F98: =text(D98,"MMM") -> Nov | G98: =Day(D98) -> 19 | H98: =year(D98) -> 2012 | I98: 41260 | J98: =DATEDIF(D98,I98,"D") -> 28 | K98: M | L98: #N/A | P98: Offline | Q98: 8959 | R98: 421.89 | S98: 364.69 | T98: =MULTIPLY(Q98,R98) -> 3779712.5 | U98: =MULTIPLY(Q99,S99) -> 4031167.8 | V98: =MINUS(T98,U98) -> -251455.33 | W98: =Q98/totals!B$2 -> 0.0013622698 | X98: =W98+X97 -> 0.070285914 | Y98: =T98/totals!B$5 -> 0.0022205788 | Z98: =Z97+Y98 -> 0.059097934 | AA98: =V98/totals!B$4 -> -0.00050139586 | AB98: =AB97+AA98 -> 0.057974247
A99: 8681 | B99: =VLOOKUP($A99,product_category,2, False) -> Office Supplies | C99: 160578763 | D99: 42274 | E99: =month(D99) -> 9 | F99: =text(D99,"MMM") -> Sep | G99: =Day(D99) -> 27 | H99: =year(D99) -> 2015 | I99: 42307 | J99: =DATEDIF(D99,I99,"D") -> 33 | K99: L | L99: ROU | M99: =VLOOKUP(L99,countries, 2,false) -> Romania | N99: =VLOOKUP(L99,countries, 4,false) -> Europe | O99: =VLOOKUP(L99,countries, 5,false) -> Eastern Europe | P99: Online | Q99: 7679 | R99: 651.21 | S99: 524.96 | T99: =MULTIPLY(Q99,R99) -> 5000641.6 | U99: =MULTIPLY(Q100,S100) -> 494842.44 | V99: =MINUS(T99,U99) -> 4505799.2 | W99: =Q99/totals!B$2 -> 0.0011676381 | X99: =W99+X98 -> 0.071453552 | Y99: =T99/totals!B$5 -> 0.0029378739 | Z99: =Z98+Y99 -> 0.062035808 | AA99: =V99/totals!B$4 -> 0.0089844548 | AB99: =AB98+AA99 -> 0.066958702
A100: 3127 | B100: =VLOOKUP($A100,product_category,2, False) -> Personal Care | C100: 160751283 | D100: 40845 | E100: =month(D100) -> 10 | F100: =text(D100,"MMM") -> Oct | G100: =Day(D100) -> 29 | H100: =year(D100) -> 2011 | I100: 40860 | J100: =DATEDIF(D100,I100,"D") -> 15 | K100: C | L100: LVA | M100: =VLOOKUP(L100,countries, 2,false) -> Latvia | N100: =VLOOKUP(L100,countries, 4,false) -> Europe | O100: =VLOOKUP(L100,countries, 5,false) -> Northern Europe | P100: Offline | Q100: 8732 | R100: 81.73 | S100: 56.67 | T100: =MULTIPLY(Q100,R100) -> 713666.36 | U100: =MULTIPLY(Q101,S101) -> 130611.68 | V100: =MINUS(T100,U100) -> 583054.68 | W100: =Q100/totals!B$2 -> 0.0013277531 | X100: =W100+X99 -> 0.072781305 | Y100: =T100/totals!B$5 -> 0.00041927856 | Z100: =Z99+Y100 -> 0.062455087 | AA100: =V100/totals!B$4 -> 0.001162597 | AB100: =AB99+AA100 -> 0.068121299
A101: 8293 | B101: =VLOOKUP($A101,product_category,2, False) -> Cosmetics | C101: 161399304 | D101: 40238 | E101: =month(D101) -> 3 | F101: =text(D101,"MMM") -> Mar | G101: =Day(D101) -> 1 | H101: =year(D101) -> 2010 | I101: 40252 | J101: =DATEDIF(D101,I101,"D") -> 14 | K101: L | L101: SVK | M101: =VLOOKUP(L101,countries, 2,false) -> Slovakia | N101: =VLOOKUP(L101,countries, 4,false) -> Europe | O101: =VLOOKUP(L101,countries, 5,false) -> Eastern Europe | P101: online | Q101: 496 | R101: 437.2 | S101: 263.33 | T101: =MULTIPLY(Q101,R101) -> 216851.2 | U101: =MULTIPLY(Q102,S102) -> 761837.41 | V101: =MINUS(T101,U101) -> -544986.21 | W101: =Q101/totals!B$2 -> 7.5419781e-05 | X101: =W101+X100 -> 0.072856725 | Y101: =T101/totals!B$5 -> 0.00012739995 | Z101: =Z100+Y101 -> 0.062582487 | AA101: =V101/totals!B$4 -> -0.0010866894 | AB101: =AB100+AA101 -> 0.067034609
A102: 8875 | B102: =VLOOKUP($A102,product_category,2, False) -> Meat | C102: 161607444 | D102: 41143 | E102: =month(D102) -> 8 | F102: =text(D102,"MMM") -> Aug | G102: =Day(D102) -> 22 | H102: =year(D102) -> 2012 | I102: 41185 | J102: =DATEDIF(D102,I102,"D") -> 42 | K102: L | L102: ROU | M102: =VLOOKUP(L102,countries, 2,false) -> Romania | N102: =VLOOKUP(L102,countries, 4,false) -> Europe | O102: =VLOOKUP(L102,countries, 5,false) -> Eastern Europe | P102: Offline | Q102: 2089 | R102: 421.89 | S102: 364.69 | T102: =MULTIPLY(Q102,R102) -> 881328.21 | U102: =MULTIPLY(Q103,S103) -> 95549.44 | V102: =MINUS(T102,U102) -> 785778.77 | W102: =Q102/totals!B$2 -> 0.00031764501 | X102: =W102+X101 -> 0.07317437 | Y102: =T102/totals!B$5 -> 0.00051777979 | Z102: =Z101+Y102 -> 0.063100266 | AA102: =V102/totals!B$4 -> 0.0015668239 | AB102: =AB101+AA102 -> 0.068601433
A103: 2455 | B103: =VLOOKUP($A103,product_category,2, False) -> Clothes | C103: 161812150 | D103: 41222 | E103: =month(D103) -> 11 | F103: =text(D103,"MMM") -> Nov | G103: =Day(D103) -> 9 | H103: =year(D103) -> 2012 | I103: 41225 | J103: =DATEDIF(D103,I103,"D") -> 3 | K103: C | L103: DNK | M103: =VLOOKUP(L103,countries, 2,false) -> Denmark | N103: =VLOOKUP(L103,countries, 4,false) -> Europe | O103: =VLOOKUP(L103,countries, 5,false) -> Northern Europe | P103: Online | Q103: 2666 | R103: 109.28 | S103: 35.84 | T103: =MULTIPLY(Q103,R103) -> 291340.48 | U103: =MULTIPLY(Q104,S104) -> 82590.42 | V103: =MINUS(T103,U103) -> 208750.06 | W103: =Q103/totals!B$2 -> 0.00040538132 | X103: =W103+X102 -> 0.073579751 | Y103: =T103/totals!B$5 -> 0.00017116236 | Z103: =Z102+Y103 -> 0.063271429 | AA103: =V103/totals!B$4 -> 0.00041624258 | AB103: =AB102+AA103 -> 0.069017676
...

Sheet ABC analysis
E1: percentile units sold | F1: percentile total revenue | G1: percentile total profit
E2: =B2/sum(B$2:B$13) -> 0.10230889 | F2: =C2/sum(C$2:C$13) -> 0.25044801 | G2: =D2/sum(D$2:D$13) -> 0.62340611
E3: =B3/sum(B$2:B$13) -> 0.1213393 | F3: =C3/sum(C$2:C$13) -> 0.1994182 | G3: =D3/sum(D$2:D$13) -> 0.48221921
E4: =B4/sum(B$2:B$13) -> 0.064639509 | F4: =C4/sum(C$2:C$13) -> 0.16238024 | G4: =D4/sum(D$2:D$13) -> 0.39172304
E5: =B5/sum(B$2:B$13) -> 0.085146078 | F5: =C5/sum(C$2:C$13) -> 0.13503522 | G5: =D5/sum(D$2:D$13) -> -0.099545337
E6: =B6/sum(B$2:B$13) -> 0.14441065 | F6: =C6/sum(C$2:C$13) -> 0.082828536 | G6: =D6/sum(D$2:D$13) -> 0.1018468
E7: =B7/sum(B$2:B$13) -> 0.091114989 | F7: =C7/sum(C$2:C$13) -> 0.052767059 | G7: =D7/sum(D$2:D$13) -> -0.061601213
E8: =B8/sum(B$2:B$13) -> 0.044795071 | F8: =C8/sum(C$2:C$13) -> 0.042986312 | G8: =D8/sum(D$2:D$13) -> 0.05925738
E9: =B9/sum(B$2:B$13) -> 0.15765325 | F9: =C9/sum(C$2:C$13) -> 0.028120454 | G9: =D9/sum(D$2:D$13) -> -0.070835919
E10: =B10/sum(B$2:B$13) -> 0.047137844 | F10: =C10/sum(C$2:C$13) -> 0.019363933 | G10: =D10/sum(D$2:D$13) -> -0.11455335
E11: =B11/sum(B$2:B$13) -> 0.050421232 | F11: =C11/sum(C$2:C$13) -> 0.015490952 | G11: =D11/sum(D$2:D$13) -> -0.089967276
E12: =B12/sum(B$2:B$13) -> 0.010794673 | F12: =C12/sum(C$2:C$13) -> 0.0083469337 | G12: =D12/sum(D$2:D$13) -> -0.1576391
E13: =B13/sum(B$2:B$13) -> 0.080238523 | F13: =C13/sum(C$2:C$13) -> 0.0028141532 | G13: =D13/sum(D$2:D$13) -> -0.064310343

Sheet products
A1: id | B1: item_type
A2: 2103 | B2: Cereal
A3: 7940 | B3: Household
A4: 2455 | B4: Clothes
A5: 1270 | B5: Beverages
A6: 8681 | B6: Office Supplies
A7: 4594 | B7: Fruits
A8: 5988 | B8: Vegetables
A9: 7331 | B9: Baby Food
A10: 8875 | B10: Meat
A11: 8293 | B11: Cosmetics
A12: 8969 | B12: Snacks
A13: 3127 | B13: Personal Care

Sheet totals
A2: total units sold | B2: =sum(events!Q2:Q1331) -> 6576524
A3: total orders | B3: =count(events!C2:C1001) -> 1330
A4: total profit | B4: =sum(events!V2:V1331) -> 5.0151058e+08 | W4: =Q2/B2 -> 0
A5: total revenue | B5: =sum(events!T2:T1331) -> 1702129408
A6: total countries | B6: =countif(countries!B2:B250,"*") -> 249

Sheet performance by channel

Sheet performance by category

Sheet performance by country

Sheet performance by region

Sheet performance by subregion

Sheet time of shipment performance
I1: region | J1: time of shipment | K1: total profit
I2: Asia | J2: 25.5 | K2: 18934359
I3: Europe | J3: 25 | K3: 4.5774499e+08

Sheet performance by year and month

Sheet profit by country
